{"meta":{"last_updated_at":"2025-03-03T23:59:59Z"},"data":{"ADA":{"code":"ADA","value":1.1710129156},"AED":{"code":"AED","value":3.6716806649},"AFN":{"code":"AFN","value":73.0770118218},"ALL":{"code":"ALL","value":94.6986181487},"AMD":{"code":"AMD","value":392.3581498305},"ANG":{"code":"ANG","value":1.7861901859},"AOA":{"code":"AOA","value":905.2692479352},"ARB":{"code":"ARB","value":2.5548256164},"ARS":{"code":"ARS","value":1063.4847622507},"AUD":{"code":"AUD","value":1.6086203106},"AVAX":{"code":"AVAX","value":0.0477651053},"AWG":{"code":"AWG","value":1.79},"AZN":{"code":"AZN","value":1.7},"BAM":{"code":"BAM","value":1.8641002612},"BBD":{"code":"BBD","value":2},"BDT":{"code":"BDT","value":121.8503909001},"BGN":{"code":"BGN","value":1.8619103188},"BHD":{"code":"BHD","value":0.376},"BIF":{"code":"BIF","value":2916.1652181031},"BMD":{"code":"BMD","value":1},"BNB":{"code":"BNB","value":0.0017443327},"BND":{"code":"BND","value":1.3451202643},"BOB":{"code":"BOB","value":6.9221711603},"BRL":{"code":"BRL","value":5.9052809084},"BSD":{"code":"BSD","value":1},"BTC":{"code":"BTC","value":1.16281e-5},"BTN":{"code":"BTN","value":83.8612051794},"BWP":{"code":"BWP","value":13.844191845},"BYN":{"code":"BYN","value":3.270783987},"BYR":{"code":"BYR","value":32707.855248457},"BZD":{"code":"BZD","value":2},"CAD":{"code":"CAD","value":1.4489202804},"CDF":{"code":"CDF","value":2853.4994376077},"CHF":{"code":"CHF","value":0.8966501079},"CLF":{"code":"CLF","value":0.0242500031},"CLP":{"code":"CLP","value":950.5208706837},"CNY":{"code":"CNY","value":7.2842008601},"COP":{"code":"COP","value":4107.6346912369},"CRC":{"code":"CRC","value":504.314935108},"CUC":{"code":"CUC","value":1},"CUP":{"code":"CUP","value":24},"CVE":{"code":"CVE","value":105.1171991961},"CZK":{"code":"CZK","value":23.8469441439},"DAI":{"code":"DAI","value":1.0016049772},"DJF":{"code":"DJF","value":177.721},"DKK":{"code":"DKK","value":7.1110009413},"DOP":{"code":"DOP","value":62.2297591615},"DOT":{"code":"DOT","value":0.2235771469},"DZD":{"code":"DZD","value":135.2692175153},"EGP":{"code":"EGP","value":50.6303675771},"ERN":{"code":"ERN","value":15},"ETB":{"code":"ETB","value":125.553656509},"ETH":{"code":"ETH","value":0.0004670424},"EUR":{"code":"EUR","value":0.9537300988},"FJD":{"code":"FJD","value":2.319650351},"FKP":{"code":"FKP","value":0.7873775105},"GBP":{"code":"GBP","value":0.7872600946},"GEL":{"code":"GEL","value":2.7679604406},"GGP":{"code":"GGP","value":0.7873772188},"GHS":{"code":"GHS","value":15.4385430798},"GIP":{"code":"GIP","value":0.7873775144},"GMD":{"code":"GMD","value":70.8047521404},"GNF":{"code":"GNF","value":8660.7161205172},"GTQ":{"code":"GTQ","value":7.6976508374},"GYD":{"code":"GYD","value":208.8322925613},"HKD":{"code":"HKD","value":7.7734010317},"HNL":{"code":"HNL","value":25.5937930467},"HRK":{"code":"HRK","value":6.6645310212},"HTG":{"code":"HTG","value":132.9224025316},"HUF":{"code":"HUF","value":381.4183955196},"IDR":{"code":"IDR","value":16457.179382464},"ILS":{"code":"ILS","value":3.6032404188},"IMP":{"code":"IMP","value":0.7873768389},"INR":{"code":"INR","value":87.1991848172},"IQD":{"code":"IQD","value":1307.7161400872},"IRR":{"code":"IRR","value":41987.28457583},"ISK":{"code":"ISK","value":139.1976517775},"JEP":{"code":"JEP","value":0.7873768067},"JMD":{"code":"JMD","value":156.5307284643},"JOD":{"code":"JOD","value":0.71},"JPY":{"code":"JPY","value":149.2352091562},"KES":{"code":"KES","value":129.090995485},"KGS":{"code":"KGS","value":87.0267721751},"KHR":{"code":"KHR","value":4002.6299172615},"KMF":{"code":"KMF","value":468.7427396729},"KPW":{"code":"KPW","value":900.0339522443},"KRW":{"code":"KRW","value":1456.7442560747},"KWD":{"code":"KWD","value":0.3083600495},"KYD":{"code":"KYD","value":0.83333},"KZT":{"code":"KZT","value":500.1677755381},"LAK":{"code":"LAK","value":21563.42150524},"LBP":{"code":"LBP","value":89533.403043536},"LKR":{"code":"LKR","value":293.7090571688},"LRD":{"code":"LRD","value":198.6475155743},"LSL":{"code":"LSL","value":18.5191734369},"LTC":{"code":"LTC","value":0.0090977234},"LTL":{"code":"LTL","value":3.2933643538},"LVL":{"code":"LVL","value":0.6703478395},"LYD":{"code":"LYD","value":4.889880722},"MAD":{"code":"MAD","value":9.9075017209},"MATIC":{"code":"MATIC","value":3.9482552862},"MDL":{"code":"MDL","value":18.5474333095},"MGA":{"code":"MGA","value":4726.3731547053},"MKD":{"code":"MKD","value":58.488316209},"MMK":{"code":"MMK","value":2097.6440308117},"MNT":{"code":"MNT","value":3469.8870772474},"MOP":{"code":"MOP","value":7.9335209582},"MRO":{"code":"MRO","value":356.999828},"MRU":{"code":"MRU","value":39.9958760658},"MUR":{"code":"MUR","value":46.3812151723},"MVR":{"code":"MVR","value":15.4463428083},"MWK":{"code":"MWK","value":1733.3241081345},"MXN":{"code":"MXN","value":20.7351432541},"MYR":{"code":"MYR","value":4.458590536},"MZN":{"code":"MZN","value":63.5192226581},"NAD":{"code":"NAD","value":18.5640422055},"NGN":{"code":"NGN","value":1498.0123380828},"NIO":{"code":"NIO","value":36.7782117655},"NOK":{"code":"NOK","value":11.1951416207},"NPR":{"code":"NPR","value":139.0543645937},"NZD":{"code":"NZD","value":1.7818803122},"OMR":{"code":"OMR","value":0.3839500551},"OP":{"code":"OP","value":1.0169487984},"PAB":{"code":"PAB","value":0.9987601001},"PEN":{"code":"PEN","value":3.6893804242},"PGK":{"code":"PGK","value":4.0132106576},"PHP":{"code":"PHP","value":57.688066566},"PKR":{"code":"PKR","value":279.4769930239},"PLN":{"code":"PLN","value":3.9649107004},"PYG":{"code":"PYG","value":7940.8464757341},"QAR":{"code":"QAR","value":3.6386706388},"RON":{"code":"RON","value":4.7450508118},"RSD":{"code":"RSD","value":111.298761335},"RUB":{"code":"RUB","value":89.7136850034},"RWF":{"code":"RWF","value":1399.628663834},"SAR":{"code":"SAR","value":3.7449806479},"SBD":{"code":"SBD","value":8.5039666073},"SCR":{"code":"SCR","value":14.9548518317},"SDG":{"code":"SDG","value":601.5},"SEK":{"code":"SEK","value":10.5073116863},"SGD":{"code":"SGD","value":1.3461401391},"SHP":{"code":"SHP","value":0.7872601296},"SLE":{"code":"SLE","value":22.7725474562},"SLL":{"code":"SLL","value":22731.635054717},"SOL":{"code":"SOL","value":0.0070004034},"SOS":{"code":"SOS","value":565.7897509672},"SRD":{"code":"SRD","value":35.2792048241},"STD":{"code":"STD","value":23581.89395087},"STN":{"code":"STN","value":23.5818997814},"SVC":{"code":"SVC","value":8.75},"SYP":{"code":"SYP","value":13002.088482409},"SZL":{"code":"SZL","value":18.5949026332},"THB":{"code":"THB","value":34.0380150026},"TJS":{"code":"TJS","value":10.8368619023},"TMT":{"code":"TMT","value":3.5},"TND":{"code":"TND","value":3.1562505714},"TOP":{"code":"TOP","value":2.4097702724},"TRY":{"code":"TRY","value":36.4278951364},"TTD":{"code":"TTD","value":6.776841204},"TWD":{"code":"TWD","value":32.9203464855},"TZS":{"code":"TZS","value":2571.9991132453},"UAH":{"code":"UAH","value":41.5419349497},"UGX":{"code":"UGX","value":3674.9493551252},"USD":{"code":"USD","value":1},"USDC":{"code":"USDC","value":1.0039882036},"USDT":{"code":"USDT","value":1.0010018295},"UYU":{"code":"UYU","value":42.61984643},"UZS":{"code":"UZS","value":12887.588692129},"VEF":{"code":"VEF","value":6440362.6497352},"VES":{"code":"VES","value":64.4036439636},"VND":{"code":"VND","value":25563.090423272},"VUV":{"code":"VUV","value":124.8157968061},"WST":{"code":"WST","value":2.8392917478},"XAF":{"code":"XAF","value":625.4781598108},"XAG":{"code":"XAG","value":0.0315838834},"XAU":{"code":"XAU","value":0.0003458827},"XCD":{"code":"XCD","value":2.7},"XDR":{"code":"XDR","value":0.7616800801},"XOF":{"code":"XOF","value":625.4781231574},"XPD":{"code":"XPD","value":0.0010638666},"XPF":{"code":"XPF","value":113.7069877787},"XPT":{"code":"XPT","value":0.001046044},"XRP":{"code":"XRP","value":0.419970438},"YER":{"code":"YER","value":246.3436142681},"ZAR":{"code":"ZAR","value":18.5890034624},"ZMK":{"code":"ZMK","value":9001.2},"ZMW":{"code":"ZMW","value":28.6630849842},"ZWG":{"code":"ZWG","value":26.5747134157},"ZWL":{"code":"ZWL","value":66402.879856896}}}