{"meta":{"last_updated_at":"2026-01-09T23:59:59Z"},"data":{"ADA":{"code":"ADA","value":2.5577628631},"AED":{"code":"AED","value":3.6734006922},"AFN":{"code":"AFN","value":66.0889090836},"ALL":{"code":"ALL","value":82.8600104947},"AMD":{"code":"AMD","value":381.2100721045},"ANG":{"code":"ANG","value":1.7880003497},"AOA":{"code":"AOA","value":912.2861510169},"ARB":{"code":"ARB","value":4.8247340469},"ARS":{"code":"ARS","value":1464.5032025032},"AUD":{"code":"AUD","value":1.495200272},"AVAX":{"code":"AVAX","value":0.0725608723},"AWG":{"code":"AWG","value":1.79},"AZN":{"code":"AZN","value":1.7},"BAM":{"code":"BAM","value":1.673940212},"BBD":{"code":"BBD","value":2},"BDT":{"code":"BDT","value":122.1700238784},"BGN":{"code":"BGN","value":1.6650003009},"BHD":{"code":"BHD","value":0.376},"BIF":{"code":"BIF","value":2959.7705600369},"BMD":{"code":"BMD","value":1},"BNB":{"code":"BNB","value":0.0011127271},"BND":{"code":"BND","value":1.2872002496},"BOB":{"code":"BOB","value":6.9400012234},"BRL":{"code":"BRL","value":5.3718009203},"BSD":{"code":"BSD","value":1},"BTC":{"code":"BTC","value":1.10377e-5},"BTN":{"code":"BTN","value":90.2605383547},"BWP":{"code":"BWP","value":13.0719015813},"BYN":{"code":"BYN","value":2.924995375},"BYR":{"code":"BYR","value":29249.951236262},"BZD":{"code":"BZD","value":2},"CAD":{"code":"CAD","value":1.3913402425},"CDF":{"code":"CDF","value":2146.1102999376},"CHF":{"code":"CHF","value":0.8011201134},"CLF":{"code":"CLF","value":0.0225000033},"CLP":{"code":"CLP","value":893.3301111291},"CNY":{"code":"CNY","value":6.9772010804},"COP":{"code":"COP","value":3713.4705432114},"CRC":{"code":"CRC","value":497.2515826836},"CUC":{"code":"CUC","value":1},"CUP":{"code":"CUP","value":24},"CVE":{"code":"CVE","value":94.7800160987},"CZK":{"code":"CZK","value":20.8679040549},"DAI":{"code":"DAI","value":0.9990563443},"DJF":{"code":"DJF","value":177.721},"DKK":{"code":"DKK","value":6.4223410757},"DOP":{"code":"DOP","value":63.3000090282},"DOT":{"code":"DOT","value":0.4804377495},"DZD":{"code":"DZD","value":130.4900190041},"EGP":{"code":"EGP","value":47.2300072405},"ERN":{"code":"ERN","value":15},"ETB":{"code":"ETB","value":155.400020241},"ETH":{"code":"ETH","value":0.0003242238},"EUR":{"code":"EUR","value":0.8594001579},"FJD":{"code":"FJD","value":2.2743002782},"FKP":{"code":"FKP","value":0.7458930197},"GBP":{"code":"GBP","value":0.7461701003},"GEL":{"code":"GEL","value":2.698200469},"GGP":{"code":"GGP","value":0.7458929768},"GHS":{"code":"GHS","value":10.7027012004},"GIP":{"code":"GIP","value":0.7458929901},"GMD":{"code":"GMD","value":74.0000134117},"GNF":{"code":"GNF","value":8757.0015919954},"GTQ":{"code":"GTQ","value":7.6680014567},"GYD":{"code":"GYD","value":208.9800229158},"HKD":{"code":"HKD","value":7.794701457},"HNL":{"code":"HNL","value":26.4507044563},"HRK":{"code":"HRK","value":6.4747248455},"HTG":{"code":"HTG","value":132.9800248147},"HUF":{"code":"HUF","value":331.3100561062},"IDR":{"code":"IDR","value":16834.003279459},"ILS":{"code":"ILS","value":3.1511806184},"IMP":{"code":"IMP","value":0.7458929697},"INR":{"code":"INR","value":90.266512245},"IQD":{"code":"IQD","value":1310.5001381605},"IRR":{"code":"IRR","value":1000260.1499297},"ISK":{"code":"ISK","value":126.4800162211},"JEP":{"code":"JEP","value":0.7458929575},"JMD":{"code":"JMD","value":157.9390238071},"JOD":{"code":"JOD","value":0.71},"JPY":{"code":"JPY","value":157.930019985},"KES":{"code":"KES","value":128.9959800033},"KGS":{"code":"KGS","value":87.4500167231},"KHR":{"code":"KHR","value":4020.0005012125},"KMF":{"code":"KMF","value":422.9700645807},"KPW":{"code":"KPW","value":900.0231047415},"KRW":{"code":"KRW","value":1458.6352455757},"KWD":{"code":"KWD","value":0.306500056},"KYD":{"code":"KYD","value":0.83333},"KZT":{"code":"KZT","value":510.3500747797},"LAK":{"code":"LAK","value":21517.003764648},"LBP":{"code":"LBP","value":89500.012683268},"LKR":{"code":"LKR","value":309.1700313873},"LRD":{"code":"LRD","value":179.9800350706},"LSL":{"code":"LSL","value":16.4800017463},"LTC":{"code":"LTC","value":0.0122851312},"LTL":{"code":"LTL","value":2.9671417938},"LVL":{"code":"LVL","value":0.6039467174},"LYD":{"code":"LYD","value":5.4241007614},"MAD":{"code":"MAD","value":9.2276017835},"MATIC":{"code":"MATIC","value":6.3917572721},"MDL":{"code":"MDL","value":16.8300029981},"MGA":{"code":"MGA","value":4600.000723924},"MKD":{"code":"MKD","value":52.7400060468},"MMK":{"code":"MMK","value":2098.6803922237},"MNT":{"code":"MNT","value":3560.3600113587},"MOP":{"code":"MOP","value":8.028501067},"MRO":{"code":"MRO","value":356.999828},"MRU":{"code":"MRU","value":39.885075125},"MUR":{"code":"MUR","value":46.7000084837},"MVR":{"code":"MVR","value":15.4600026227},"MWK":{"code":"MWK","value":1733.6742940978},"MXN":{"code":"MXN","value":17.9770018157},"MYR":{"code":"MYR","value":4.0740006084},"MZN":{"code":"MZN","value":63.5700119145},"NAD":{"code":"NAD","value":16.491802833},"NGN":{"code":"NGN","value":1420.1602395024},"NIO":{"code":"NIO","value":36.7934197221},"NOK":{"code":"NOK","value":10.0967311229},"NPR":{"code":"NPR","value":144.1750278639},"NZD":{"code":"NZD","value":1.7448002294},"OMR":{"code":"OMR","value":0.3850000717},"OP":{"code":"OP","value":3.177494479},"PAB":{"code":"PAB","value":1.0000001441},"PEN":{"code":"PEN","value":3.3626006291},"PGK":{"code":"PGK","value":4.2580005188},"PHP":{"code":"PHP","value":59.290011839},"PKR":{"code":"PKR","value":279.8500523455},"PLN":{"code":"PLN","value":3.619800484},"PYG":{"code":"PYG","value":6567.0011349989},"QAR":{"code":"QAR","value":3.6410003742},"RON":{"code":"RON","value":4.374700572},"RSD":{"code":"RSD","value":100.8420120028},"RUB":{"code":"RUB","value":79.000010922},"RWF":{"code":"RWF","value":1457.0102686825},"SAR":{"code":"SAR","value":3.750300588},"SBD":{"code":"SBD","value":8.1382476733},"SCR":{"code":"SCR","value":14.9250016997},"SDG":{"code":"SDG","value":601.5},"SEK":{"code":"SEK","value":9.211551118},"SGD":{"code":"SGD","value":1.287230157},"SHP":{"code":"SHP","value":0.7457000885},"SLE":{"code":"SLE","value":22.8102563578},"SLL":{"code":"SLL","value":22746.003878688},"SOL":{"code":"SOL","value":0.0073625709},"SOS":{"code":"SOS","value":569.3000768455},"SRD":{"code":"SRD","value":38.0800058523},"STD":{"code":"STD","value":21264.367836138},"STN":{"code":"STN","value":21.2643686499},"SVC":{"code":"SVC","value":8.75},"SYP":{"code":"SYP","value":111.570250984},"SZL":{"code":"SZL","value":16.5030031949},"THB":{"code":"THB","value":31.3600051287},"TJS":{"code":"TJS","value":9.3086017338},"TMT":{"code":"TMT","value":3.5},"TND":{"code":"TND","value":2.8800004229},"TOP":{"code":"TOP","value":2.4125004482},"TRX":{"code":"TRX","value":3.3519133362},"TRY":{"code":"TRY","value":43.0437055648},"TTD":{"code":"TTD","value":6.7303009545},"TWD":{"code":"TWD","value":31.642005725},"TZS":{"code":"TZS","value":2483.0004602344},"UAH":{"code":"UAH","value":43.1154054987},"UGX":{"code":"UGX","value":3598.9005801758},"USD":{"code":"USD","value":1},"USDC":{"code":"USDC","value":0.9982588427},"USDT":{"code":"USDT","value":1.0004350433},"UYU":{"code":"UYU","value":38.9850057395},"UZS":{"code":"UZS","value":12130.002120561},"VEF":{"code":"VEF","value":32352310.052478},"VES":{"code":"VES","value":323.5231188255},"VND":{"code":"VND","value":26230.004634126},"VUV":{"code":"VUV","value":120.5958396903},"WST":{"code":"WST","value":2.7839823556},"XAF":{"code":"XAF","value":563.8100629167},"XAG":{"code":"XAG","value":0.0125135378},"XAU":{"code":"XAU","value":0.0002217387},"XCD":{"code":"XCD","value":2.7},"XCG":{"code":"XCG","value":1.8020064289},"XDR":{"code":"XDR","value":0.7327200918},"XOF":{"code":"XOF","value":563.8100874087},"XPD":{"code":"XPD","value":0.0005499139},"XPF":{"code":"XPF","value":102.6200129162},"XPT":{"code":"XPT","value":0.000437449},"XRP":{"code":"XRP","value":0.4775887494},"YER":{"code":"YER","value":238.3900250776},"ZAR":{"code":"ZAR","value":16.4808023489},"ZMK":{"code":"ZMK","value":9001.2},"ZMW":{"code":"ZMW","value":19.5000031654},"ZWG":{"code":"ZWG","value":25.7638196564},"ZWL":{"code":"ZWL","value":64376.681631287}}}