{"meta":{"last_updated_at":"2025-06-05T23:59:59Z"},"data":{"ADA":{"code":"ADA","value":1.5953083447},"AED":{"code":"AED","value":3.6718905595},"AFN":{"code":"AFN","value":69.7896374433},"ALL":{"code":"ALL","value":85.6589642958},"AMD":{"code":"AMD","value":383.0670933978},"ANG":{"code":"ANG","value":1.7027402763},"AOA":{"code":"AOA","value":911.6314501736},"ARB":{"code":"ARB","value":3.0834952009},"ARS":{"code":"ARS","value":1186.818100829},"AUD":{"code":"AUD","value":1.535780163},"AVAX":{"code":"AVAX","value":0.0532394337},"AWG":{"code":"AWG","value":1.79},"AZN":{"code":"AZN","value":1.7},"BAM":{"code":"BAM","value":1.7067402958},"BBD":{"code":"BBD","value":2},"BDT":{"code":"BDT","value":122.6109475049},"BGN":{"code":"BGN","value":1.710540212},"BHD":{"code":"BHD","value":0.376},"BIF":{"code":"BIF","value":2930.0329530335},"BMD":{"code":"BMD","value":1},"BNB":{"code":"BNB","value":0.0015779791},"BND":{"code":"BND","value":1.285710223},"BOB":{"code":"BOB","value":6.9038707015},"BRL":{"code":"BRL","value":5.5860811015},"BSD":{"code":"BSD","value":1},"BTC":{"code":"BTC","value":9.8358e-6},"BTN":{"code":"BTN","value":78.4376332856},"BWP":{"code":"BWP","value":13.3713517517},"BYN":{"code":"BYN","value":3.2749959574},"BYR":{"code":"BYR","value":32749.96144569},"BZD":{"code":"BZD","value":2},"CAD":{"code":"CAD","value":1.3667401785},"CDF":{"code":"CDF","value":2862.6867993964},"CHF":{"code":"CHF","value":0.8194001292},"CLF":{"code":"CLF","value":0.0233400032},"CLP":{"code":"CLP","value":929.5393255437},"CNY":{"code":"CNY","value":7.1711011715},"COP":{"code":"COP","value":4109.8485621863},"CRC":{"code":"CRC","value":509.3467280343},"CUC":{"code":"CUC","value":1},"CUP":{"code":"CUP","value":24},"CVE":{"code":"CVE","value":96.495018454},"CZK":{"code":"CZK","value":21.6268843008},"DAI":{"code":"DAI","value":1.000099114},"DJF":{"code":"DJF","value":177.721},"DKK":{"code":"DKK","value":6.5125506715},"DOP":{"code":"DOP","value":58.8888682734},"DOT":{"code":"DOT","value":0.2614809522},"DZD":{"code":"DZD","value":132.0913919311},"EGP":{"code":"EGP","value":49.6136458582},"ERN":{"code":"ERN","value":15},"ETB":{"code":"ETB","value":134.0058801075},"ETH":{"code":"ETH","value":0.0004134173},"EUR":{"code":"EUR","value":0.8731401294},"FJD":{"code":"FJD","value":2.2679303126},"FKP":{"code":"FKP","value":0.7363277288},"GBP":{"code":"GBP","value":0.7363401086},"GEL":{"code":"GEL","value":2.7242903761},"GGP":{"code":"GGP","value":0.736327723},"GHS":{"code":"GHS","value":10.1968214754},"GIP":{"code":"GIP","value":0.7363277001},"GMD":{"code":"GMD","value":69.8304304427},"GNF":{"code":"GNF","value":8684.3745126711},"GTQ":{"code":"GTQ","value":7.6705008662},"GYD":{"code":"GYD","value":209.4046208171},"HKD":{"code":"HKD","value":7.8447910265},"HNL":{"code":"HNL","value":26.0151244471},"HRK":{"code":"HRK","value":6.2335211112},"HTG":{"code":"HTG","value":133.1730832135},"HUF":{"code":"HUF","value":351.8409174892},"IDR":{"code":"IDR","value":16248.105567723},"ILS":{"code":"ILS","value":3.4851406055},"IMP":{"code":"IMP","value":0.7363276664},"INR":{"code":"INR","value":85.7532207912},"IQD":{"code":"IQD","value":1307.593431159},"IRR":{"code":"IRR","value":41981.656988829},"ISK":{"code":"ISK","value":126.1166830195},"JEP":{"code":"JEP","value":0.7363277001},"JMD":{"code":"JMD","value":159.0091981004},"JOD":{"code":"JOD","value":0.71},"JPY":{"code":"JPY","value":143.5474275338},"KES":{"code":"KES","value":129.3301038856},"KGS":{"code":"KGS","value":87.4394546549},"KHR":{"code":"KHR","value":4000.1037859179},"KMF":{"code":"KMF","value":430.8639527165},"KPW":{"code":"KPW","value":900.0572547091},"KRW":{"code":"KRW","value":1352.7902449149},"KWD":{"code":"KWD","value":0.3051200448},"KYD":{"code":"KYD","value":0.83333},"KZT":{"code":"KZT","value":509.4599026447},"LAK":{"code":"LAK","value":21457.082579186},"LBP":{"code":"LBP","value":89500.473624559},"LKR":{"code":"LKR","value":299.0950881386},"LRD":{"code":"LRD","value":198.6937436925},"LSL":{"code":"LSL","value":17.7774232762},"LTC":{"code":"LTC","value":0.0119342602},"LTL":{"code":"LTL","value":3.0145969536},"LVL":{"code":"LVL","value":0.6136059856},"LYD":{"code":"LYD","value":5.4406505515},"MAD":{"code":"MAD","value":9.1280911187},"MATIC":{"code":"MATIC","value":5.0052547355},"MDL":{"code":"MDL","value":17.1789921542},"MGA":{"code":"MGA","value":4508.6307869907},"MKD":{"code":"MKD","value":53.697640707},"MMK":{"code":"MMK","value":2097.0284589746},"MNT":{"code":"MNT","value":3577.6080857403},"MOP":{"code":"MOP","value":8.065621384},"MRO":{"code":"MRO","value":356.999828},"MRU":{"code":"MRU","value":39.5991590979},"MUR":{"code":"MUR","value":45.1435982643},"MVR":{"code":"MVR","value":15.4494623225},"MWK":{"code":"MWK","value":1732.5525323954},"MXN":{"code":"MXN","value":19.1472435194},"MYR":{"code":"MYR","value":4.2285106808},"MZN":{"code":"MZN","value":63.4991188672},"NAD":{"code":"NAD","value":17.6733024565},"NGN":{"code":"NGN","value":1560.969564453},"NIO":{"code":"NIO","value":36.7987640525},"NOK":{"code":"NOK","value":10.0683312966},"NPR":{"code":"NPR","value":137.2200360796},"NZD":{"code":"NZD","value":1.6552202618},"OMR":{"code":"OMR","value":0.3838200681},"OP":{"code":"OP","value":1.6899294646},"PAB":{"code":"PAB","value":0.9990401343},"PEN":{"code":"PEN","value":3.6217505485},"PGK":{"code":"PGK","value":4.0802904809},"PHP":{"code":"PHP","value":55.631867119},"PKR":{"code":"PKR","value":281.8815498859},"PLN":{"code":"PLN","value":3.7342704472},"PYG":{"code":"PYG","value":7987.0560509091},"QAR":{"code":"QAR","value":3.6374003688},"RON":{"code":"RON","value":4.4077106943},"RSD":{"code":"RSD","value":102.1383534616},"RUB":{"code":"RUB","value":77.1946851466},"RWF":{"code":"RWF","value":1414.6505001204},"SAR":{"code":"SAR","value":3.7466006889},"SBD":{"code":"SBD","value":8.5096027276},"SCR":{"code":"SCR","value":14.6557617988},"SDG":{"code":"SDG","value":601.5},"SEK":{"code":"SEK","value":9.5647518129},"SGD":{"code":"SGD","value":1.2862501337},"SHP":{"code":"SHP","value":0.7363401338},"SLE":{"code":"SLE","value":22.7700828264},"SLL":{"code":"SLL","value":22693.551772585},"SOL":{"code":"SOL","value":0.0069205593},"SOS":{"code":"SOS","value":571.2487588586},"SRD":{"code":"SRD","value":36.5973558643},"STD":{"code":"STD","value":21631.680928776},"STN":{"code":"STN","value":21.6316825723},"SVC":{"code":"SVC","value":8.75},"SYP":{"code":"SYP","value":13001.857833384},"SZL":{"code":"SZL","value":17.7030522697},"THB":{"code":"THB","value":32.6113746165},"TJS":{"code":"TJS","value":9.8628919468},"TMT":{"code":"TMT","value":3.5},"TND":{"code":"TND","value":2.9377504142},"TOP":{"code":"TOP","value":2.3574403541},"TRY":{"code":"TRY","value":39.2606475768},"TTD":{"code":"TTD","value":6.6925509017},"TWD":{"code":"TWD","value":29.9413938289},"TZS":{"code":"TZS","value":2651.0687637},"UAH":{"code":"UAH","value":41.5875661578},"UGX":{"code":"UGX","value":3638.3228089642},"USD":{"code":"USD","value":1},"USDC":{"code":"USDC","value":1.0018843054},"USDT":{"code":"USDT","value":0.9993560469},"UYU":{"code":"UYU","value":41.5575969071},"UZS":{"code":"UZS","value":12789.349022959},"VEF":{"code":"VEF","value":9808494.779483},"VES":{"code":"VES","value":98.0849436475},"VND":{"code":"VND","value":26039.942429291},"VUV":{"code":"VUV","value":120.350559388},"WST":{"code":"WST","value":2.746275004},"XAF":{"code":"XAF","value":572.6389856499},"XAG":{"code":"XAG","value":0.0279936458},"XAU":{"code":"XAU","value":0.000297428},"XCD":{"code":"XCD","value":2.7},"XDR":{"code":"XDR","value":0.7337501098},"XOF":{"code":"XOF","value":572.6389996021},"XPD":{"code":"XPD","value":0.0009920507},"XPF":{"code":"XPF","value":104.1095569247},"XPT":{"code":"XPT","value":0.0008772317},"XRP":{"code":"XRP","value":0.4766363272},"YER":{"code":"YER","value":242.8390785443},"ZAR":{"code":"ZAR","value":17.7105634033},"ZMK":{"code":"ZMK","value":9001.2},"ZMW":{"code":"ZMW","value":26.174984874},"ZWG":{"code":"ZWG","value":26.9450709549},"ZWL":{"code":"ZWL","value":67328.30082896}}}