{"meta":{"last_updated_at":"2023-11-05T23:59:59Z"},"data":{"ADA":{"code":"ADA","value":2.9188347855},"AED":{"code":"AED","value":3.6725203893},"AFN":{"code":"AFN","value":73.4317891322},"ALL":{"code":"ALL","value":97.5410686595},"AMD":{"code":"AMD","value":397.3714143289},"ANG":{"code":"ANG","value":1.7859202727},"AOA":{"code":"AOA","value":812.5526131973},"ARB":{"code":"ARB","value":0.9156166346},"ARS":{"code":"ARS","value":349.900646915},"AUD":{"code":"AUD","value":1.5345401805},"AVAX":{"code":"AVAX","value":0.0808192079},"AWG":{"code":"AWG","value":1.79},"AZN":{"code":"AZN","value":1.7},"BAM":{"code":"BAM","value":1.8267502861},"BBD":{"code":"BBD","value":2},"BDT":{"code":"BDT","value":110.5525785581},"BGN":{"code":"BGN","value":1.8221902017},"BHD":{"code":"BHD","value":0.376},"BIF":{"code":"BIF","value":2839.8090856443},"BMD":{"code":"BMD","value":1},"BNB":{"code":"BNB","value":0.0040880043},"BND":{"code":"BND","value":1.3527901455},"BOB":{"code":"BOB","value":6.9230507017},"BRL":{"code":"BRL","value":4.8928708594},"BSD":{"code":"BSD","value":1},"BTC":{"code":"BTC","value":2.84751e-5},"BTN":{"code":"BTN","value":81.9849561623},"BUSD":{"code":"BUSD","value":0.9978611836},"BWP":{"code":"BWP","value":13.4918213548},"BYN":{"code":"BYN","value":3.2949429916},"BYR":{"code":"BYR","value":32949.407385299},"BZD":{"code":"BZD","value":2},"CAD":{"code":"CAD","value":1.3660502242},"CDF":{"code":"CDF","value":2479.9602159208},"CHF":{"code":"CHF","value":0.8990201329},"CLF":{"code":"CLF","value":0.0236300037},"CLP":{"code":"CLP","value":875.4365140133},"CNY":{"code":"CNY","value":7.2979409447},"COP":{"code":"COP","value":3974.4820056046},"CRC":{"code":"CRC","value":533.5081899824},"CUC":{"code":"CUC","value":1},"CUP":{"code":"CUP","value":24},"CVE":{"code":"CVE","value":102.7498661429},"CZK":{"code":"CZK","value":22.7013730614},"DAI":{"code":"DAI","value":0.9994429713},"DJF":{"code":"DJF","value":177.721},"DKK":{"code":"DKK","value":6.9510907368},"DOP":{"code":"DOP","value":56.23538017},"DOT":{"code":"DOT","value":0.2094329312},"DZD":{"code":"DZD","value":136.0374212056},"EGP":{"code":"EGP","value":30.8922744197},"ERN":{"code":"ERN","value":15},"ETB":{"code":"ETB","value":54.8942261367},"ETH":{"code":"ETH","value":0.0005274001},"EUR":{"code":"EUR","value":0.9317201208},"FJD":{"code":"FJD","value":2.2528502357},"FKP":{"code":"FKP","value":0.8079824195},"GBP":{"code":"GBP","value":0.8080701125},"GEL":{"code":"GEL","value":2.6757503309},"GGP":{"code":"GGP","value":0.8079825014},"GHS":{"code":"GHS","value":11.869711503},"GIP":{"code":"GIP","value":0.8079822105},"GMD":{"code":"GMD","value":59.8568964568},"GNF":{"code":"GNF","value":8545.8029290603},"GTQ":{"code":"GTQ","value":7.8212608425},"GYD":{"code":"GYD","value":208.8168561108},"HKD":{"code":"HKD","value":7.8221108037},"HNL":{"code":"HNL","value":24.6820348053},"HRK":{"code":"HRK","value":7.0425408739},"HTG":{"code":"HTG","value":134.4180520469},"HUF":{"code":"HUF","value":353.8908982314},"IDR":{"code":"IDR","value":15704.153081381},"ILS":{"code":"ILS","value":3.9255304843},"IMP":{"code":"IMP","value":0.80798277},"INR":{"code":"INR","value":83.0822989945},"IQD":{"code":"IQD","value":1307.6962259709},"IRR":{"code":"IRR","value":41992.378977966},"ISK":{"code":"ISK","value":139.0264570119},"JEP":{"code":"JEP","value":0.8079824124},"JMD":{"code":"JMD","value":154.4403473221},"JOD":{"code":"JOD","value":0.71},"JPY":{"code":"JPY","value":149.4456975115},"KES":{"code":"KES","value":149.2166576145},"KGS":{"code":"KGS","value":88.1569738348},"KHR":{"code":"KHR","value":4105.5423846247},"KMF":{"code":"KMF","value":463.0277506737},"KPW":{"code":"KPW","value":900.0285921573},"KRW":{"code":"KRW","value":1306.3790579203},"KWD":{"code":"KWD","value":0.3083900343},"KYD":{"code":"KYD","value":0.83333},"KZT":{"code":"KZT","value":463.8010675803},"LAK":{"code":"LAK","value":20742.778018422},"LBP":{"code":"LBP","value":15003.639157931},"LKR":{"code":"LKR","value":324.1225001719},"LRD":{"code":"LRD","value":187.5945757851},"LSL":{"code":"LSL","value":18.3798220779},"LTC":{"code":"LTC","value":0.0139591561},"LTL":{"code":"LTL","value":3.2171638898},"LVL":{"code":"LVL","value":0.6548376435},"LYD":{"code":"LYD","value":4.8840109238},"MAD":{"code":"MAD","value":10.2027411774},"MATIC":{"code":"MATIC","value":1.4419684445},"MDL":{"code":"MDL","value":17.9998732473},"MGA":{"code":"MGA","value":4516.469285997},"MKD":{"code":"MKD","value":57.4268006234},"MMK":{"code":"MMK","value":2094.2048929109},"MNT":{"code":"MNT","value":3453.1192137749},"MOP":{"code":"MOP","value":8.0595610491},"MRO":{"code":"MRO","value":356.999828},"MUR":{"code":"MUR","value":44.2310470263},"MVR":{"code":"MVR","value":15.4430625097},"MWK":{"code":"MWK","value":1125.986063574},"MXN":{"code":"MXN","value":17.4655028338},"MYR":{"code":"MYR","value":4.7255407304},"MZN":{"code":"MZN","value":63.6704988897},"NAD":{"code":"NAD","value":18.2042321564},"NGN":{"code":"NGN","value":806.3790016612},"NIO":{"code":"NIO","value":36.5009527692},"NOK":{"code":"NOK","value":11.0195415238},"NPR":{"code":"NPR","value":131.3191150045},"NZD":{"code":"NZD","value":1.6677903169},"OMR":{"code":"OMR","value":0.3839100649},"OP":{"code":"OP","value":0.6482736521},"PAB":{"code":"PAB","value":0.9991801439},"PEN":{"code":"PEN","value":3.7328505678},"PGK":{"code":"PGK","value":3.6614205583},"PHP":{"code":"PHP","value":56.0604368321},"PKR":{"code":"PKR","value":284.0318162571},"PLN":{"code":"PLN","value":4.1444707599},"PYG":{"code":"PYG","value":7496.9061004185},"QAR":{"code":"QAR","value":3.6386304536},"RON":{"code":"RON","value":4.630280471},"RSD":{"code":"RSD","value":108.8564395057},"RUB":{"code":"RUB","value":91.7027771534},"RWF":{"code":"RWF","value":1227.8429161683},"SAR":{"code":"SAR","value":3.744460703},"SBD":{"code":"SBD","value":8.4417305022},"SCR":{"code":"SCR","value":14.7162916677},"SDG":{"code":"SDG","value":601.5},"SEK":{"code":"SEK","value":10.8775617582},"SGD":{"code":"SGD","value":1.3535102301},"SHP":{"code":"SHP","value":0.8080701295},"SLL":{"code":"SLL","value":21366.526615144},"SOL":{"code":"SOL","value":0.0242377413},"SOS":{"code":"SOS","value":570.49347919},"SRD":{"code":"SRD","value":38.18726574},"STD":{"code":"STD","value":22995.020519177},"SVC":{"code":"SVC","value":8.75},"SYP":{"code":"SYP","value":13001.878655198},"SZL":{"code":"SZL","value":18.2288031004},"THB":{"code":"THB","value":35.5178959579},"TJS":{"code":"TJS","value":10.7939318354},"TMT":{"code":"TMT","value":3.5},"TND":{"code":"TND","value":3.159490377},"TOP":{"code":"TOP","value":2.2781002646},"TRY":{"code":"TRY","value":28.3943738694},"TTD":{"code":"TTD","value":6.7135713342},"TWD":{"code":"TWD","value":32.1328162089},"TZS":{"code":"TZS","value":2501.3578331378},"UAH":{"code":"UAH","value":36.6857944727},"UGX":{"code":"UGX","value":3752.2791441182},"USD":{"code":"USD","value":1},"USDC":{"code":"USDC","value":0.9992845559},"USDT":{"code":"USDT","value":0.9978449243},"UYU":{"code":"UYU","value":40.0446178237},"UZS":{"code":"UZS","value":12270.833488028},"VEF":{"code":"VEF","value":3515952.2682745},"VND":{"code":"VND","value":24505.871126871},"VUV":{"code":"VUV","value":121.8540351942},"WST":{"code":"WST","value":2.7662900167},"XAF":{"code":"XAF","value":611.1700174837},"XAG":{"code":"XAG","value":0.0431993055},"XAU":{"code":"XAU","value":0.0005028402},"XCD":{"code":"XCD","value":2.7},"XDR":{"code":"XDR","value":0.76008009},"XOF":{"code":"XOF","value":611.1699883792},"XPD":{"code":"XPD","value":0.0008918417},"XPF":{"code":"XPF","value":111.1166102885},"XPT":{"code":"XPT","value":0.0010730208},"XRP":{"code":"XRP","value":1.5047116365},"YER":{"code":"YER","value":249.7002520492},"ZAR":{"code":"ZAR","value":18.2485130574},"ZMK":{"code":"ZMK","value":9001.2},"ZMW":{"code":"ZMW","value":22.2751129353},"ZWL":{"code":"ZWL","value":5707.2305586142}}}