{"meta":{"last_updated_at":"2026-06-14T23:59:59Z"},"data":{"ADA":{"code":"ADA","value":5.4696934916},"AED":{"code":"AED","value":3.6733004192},"AFN":{"code":"AFN","value":64.2540088082},"ALL":{"code":"ALL","value":82.0000091998},"AMD":{"code":"AMD","value":368.1800394086},"ANG":{"code":"ANG","value":1.7880002543},"AOA":{"code":"AOA","value":913.1160965532},"ARB":{"code":"ARB","value":11.6227182324},"ARS":{"code":"ARS","value":1428.503266566},"AUD":{"code":"AUD","value":1.4134001438},"AVAX":{"code":"AVAX","value":0.1476436441},"AWG":{"code":"AWG","value":1.79},"AZN":{"code":"AZN","value":1.7},"BAM":{"code":"BAM","value":1.6850002799},"BBD":{"code":"BBD","value":2},"BDT":{"code":"BDT","value":122.6700151261},"BGN":{"code":"BGN","value":1.6650002279},"BHD":{"code":"BHD","value":0.376},"BIF":{"code":"BIF","value":2981.1304633079},"BMD":{"code":"BMD","value":1},"BNB":{"code":"BNB","value":0.0016235836},"BND":{"code":"BND","value":1.2811002002},"BOB":{"code":"BOB","value":6.9300007205},"BRL":{"code":"BRL","value":5.063900758},"BSD":{"code":"BSD","value":1},"BTC":{"code":"BTC","value":1.52242e-5},"BTN":{"code":"BTN","value":95.1099158454},"BWP":{"code":"BWP","value":13.1234022082},"BYN":{"code":"BYN","value":2.7700004108},"BYR":{"code":"BYR","value":19600},"BZD":{"code":"BZD","value":2},"CAD":{"code":"CAD","value":1.3963901768},"CDF":{"code":"CDF","value":2266.0002514402},"CHF":{"code":"CHF","value":0.7940001416},"CLF":{"code":"CLF","value":0.022060003},"CLP":{"code":"CLP","value":899.3301572298},"CNY":{"code":"CNY","value":6.7626009099},"COP":{"code":"COP","value":3491.0804454119},"CRC":{"code":"CRC","value":454.8573210983},"CUC":{"code":"CUC","value":1},"CUP":{"code":"CUP","value":24},"CVE":{"code":"CVE","value":95.4300177337},"CZK":{"code":"CZK","value":20.8059035783},"DAI":{"code":"DAI","value":1.0002554042},"DJF":{"code":"DJF","value":177.721},"DKK":{"code":"DKK","value":6.4419812165},"DOP":{"code":"DOP","value":58.7300064544},"DOT":{"code":"DOT","value":1.00448382},"DZD":{"code":"DZD","value":133.5380265747},"EGP":{"code":"EGP","value":51.1200081555},"ERN":{"code":"ERN","value":15},"ETB":{"code":"ETB","value":159.1300196256},"ETH":{"code":"ETH","value":0.0005802037},"EUR":{"code":"EUR","value":0.8618871562},"FJD":{"code":"FJD","value":2.2365004427},"FKP":{"code":"FKP","value":0.7434475695},"GBP":{"code":"GBP","value":0.7435660881},"GEL":{"code":"GEL","value":2.6586004146},"GGP":{"code":"GGP","value":0.7434476143},"GHS":{"code":"GHS","value":11.0027012768},"GIP":{"code":"GIP","value":0.7434475687},"GMD":{"code":"GMD","value":74.8500085431},"GNF":{"code":"GNF","value":8770.0015542489},"GTQ":{"code":"GTQ","value":7.6160010754},"GYD":{"code":"GYD","value":208.9800370721},"HKD":{"code":"HKD","value":7.8349210671},"HNL":{"code":"HNL","value":26.7036038365},"HRK":{"code":"HRK","value":6.4928451433},"HTG":{"code":"HTG","value":132.93001682},"HUF":{"code":"HUF","value":302.8850490507},"IDR":{"code":"IDR","value":17920.002579826},"ILS":{"code":"ILS","value":2.9323503401},"IMP":{"code":"IMP","value":0.7434476069},"INR":{"code":"INR","value":95.0970095455},"IQD":{"code":"IQD","value":1310.5001885798},"IRR":{"code":"IRR","value":1375505.2276986},"ISK":{"code":"ISK","value":124.2800175224},"JEP":{"code":"JEP","value":0.7434475595},"JMD":{"code":"JMD","value":158.0400218508},"JOD":{"code":"JOD","value":0.71},"JPY":{"code":"JPY","value":159.9780209864},"KES":{"code":"KES","value":129.5076733693},"KGS":{"code":"KGS","value":87.4500161445},"KHR":{"code":"KHR","value":4018.0006330423},"KMF":{"code":"KMF","value":425.5600498708},"KPW":{"code":"KPW","value":900.0001393188},"KRW":{"code":"KRW","value":1510.7172129072},"KWD":{"code":"KWD","value":0.308550059},"KYD":{"code":"KYD","value":0.83333},"KZT":{"code":"KZT","value":488.4500732838},"LAK":{"code":"LAK","value":21934.003403259},"LBP":{"code":"LBP","value":89500.015496059},"LKR":{"code":"LKR","value":336.0000580946},"LRD":{"code":"LRD","value":182.3420208427},"LSL":{"code":"LSL","value":16.2800025601},"LTC":{"code":"LTC","value":0.0220744786},"LTL":{"code":"LTL","value":2.9754455265},"LVL":{"code":"LVL","value":0.6056368951},"LYD":{"code":"LYD","value":6.3739011931},"MAD":{"code":"MAD","value":9.253201759},"MATIC":{"code":"MATIC","value":13.0051849764},"MDL":{"code":"MDL","value":17.320002812},"MGA":{"code":"MGA","value":4200.0005067722},"MKD":{"code":"MKD","value":53.2100064862},"MMK":{"code":"MMK","value":2098.6803613889},"MNT":{"code":"MNT","value":3577.8648142319},"MOP":{"code":"MOP","value":8.0698015134},"MRO":{"code":"MRO","value":356.999828},"MRU":{"code":"MRU","value":39.9657045741},"MUR":{"code":"MUR","value":47.2400077029},"MVR":{"code":"MVR","value":15.4600024915},"MWK":{"code":"MWK","value":1733.6732594526},"MXN":{"code":"MXN","value":17.1688017647},"MYR":{"code":"MYR","value":4.0580004993},"MZN":{"code":"MZN","value":63.5500100608},"NAD":{"code":"NAD","value":16.2754028339},"NGN":{"code":"NGN","value":1360.2801894682},"NIO":{"code":"NIO","value":36.7972726037},"NOK":{"code":"NOK","value":9.4987610116},"NPR":{"code":"NPR","value":152.2100199098},"NZD":{"code":"NZD","value":1.7081002188},"OMR":{"code":"OMR","value":0.3850000612},"OP":{"code":"OP","value":9.2230737682},"PAB":{"code":"PAB","value":1.00000018},"PEN":{"code":"PEN","value":3.4004003987},"PGK":{"code":"PGK","value":4.3010006475},"PHP":{"code":"PHP","value":60.7470110062},"PKR":{"code":"PKR","value":278.1300453648},"PLN":{"code":"PLN","value":3.6565107139},"PYG":{"code":"PYG","value":6118.8206574557},"QAR":{"code":"QAR","value":3.6410006248},"RON":{"code":"RON","value":4.5246008921},"RSD":{"code":"RSD","value":101.4420121465},"RUB":{"code":"RUB","value":72.4860101466},"RWF":{"code":"RWF","value":1464.6101611118},"SAR":{"code":"SAR","value":3.7529903833},"SBD":{"code":"SBD","value":8.062829873},"SCR":{"code":"SCR","value":14.8167027505},"SDG":{"code":"SDG","value":601.5},"SEK":{"code":"SEK","value":9.389851197},"SGD":{"code":"SGD","value":1.2812401596},"SHP":{"code":"SHP","value":0.7451000838},"SLE":{"code":"SLE","value":22.820100219},"SLL":{"code":"SLL","value":22758.304501909},"SOL":{"code":"SOL","value":0.0140610743},"SOS":{"code":"SOS","value":571.4500643427},"SRD":{"code":"SRD","value":37.4400055185},"STD":{"code":"STD","value":21276.17990643},"STN":{"code":"STN","value":21.2761806309},"SVC":{"code":"SVC","value":8.75},"SYP":{"code":"SYP","value":110.5300189264},"SZL":{"code":"SZL","value":16.165802157},"THB":{"code":"THB","value":32.5950050543},"TJS":{"code":"TJS","value":9.3181017128},"TMT":{"code":"TMT","value":3.5},"TND":{"code":"TND","value":2.9185003145},"TOP":{"code":"TOP","value":2.3529003214},"TRX":{"code":"TRX","value":3.0961475062},"TRY":{"code":"TRY","value":46.2585069163},"TTD":{"code":"TTD","value":6.7748011616},"TWD":{"code":"TWD","value":31.6419046113},"TZS":{"code":"TZS","value":2613.0003356565},"UAH":{"code":"UAH","value":45.0506079422},"UGX":{"code":"UGX","value":3752.9004417866},"USD":{"code":"USD","value":1},"USDC":{"code":"USDC","value":1.0001940479},"USDT":{"code":"USDT","value":1.0010284665},"UYU":{"code":"UYU","value":40.5920040596},"UZS":{"code":"UZS","value":11981.811289882},"VEF":{"code":"VEF","value":58523858.746248},"VES":{"code":"VES","value":585.238543472},"VND":{"code":"VND","value":26260.002714563},"VUV":{"code":"VUV","value":118.8589031355},"WST":{"code":"WST","value":2.7221459996},"XAF":{"code":"XAF","value":565.2700924821},"XAG":{"code":"XAG","value":0.0142306908},"XAU":{"code":"XAU","value":0.0002328691},"XCD":{"code":"XCD","value":2.7},"XCG":{"code":"XCG","value":1.8006252896},"XDR":{"code":"XDR","value":0.7322000934},"XOF":{"code":"XOF","value":565.2700901337},"XPD":{"code":"XPD","value":0.0007552465},"XPF":{"code":"XPF","value":103.350014007},"XPT":{"code":"XPT","value":0.0005675474},"XRP":{"code":"XRP","value":0.8438345137},"YER":{"code":"YER","value":238.6000262921},"ZAR":{"code":"ZAR","value":16.1742022093},"ZMK":{"code":"ZMK","value":9001.2},"ZMW":{"code":"ZMW","value":17.5800018648},"ZWG":{"code":"ZWG","value":26.7826560026},"ZWL":{"code":"ZWL","value":66922.470821069}}}