{"meta":{"last_updated_at":"2024-06-28T23:59:59Z"},"data":{"ADA":{"code":"ADA","value":2.5956202076},"AED":{"code":"AED","value":3.6713004829},"AFN":{"code":"AFN","value":70.970988757},"ALL":{"code":"ALL","value":93.5386868939},"AMD":{"code":"AMD","value":387.627631651},"ANG":{"code":"ANG","value":1.7845403149},"AOA":{"code":"AOA","value":852.9935927465},"ARB":{"code":"ARB","value":1.2640446241},"ARS":{"code":"ARS","value":910.0885963192},"AUD":{"code":"AUD","value":1.4994102486},"AVAX":{"code":"AVAX","value":0.0358154042},"AWG":{"code":"AWG","value":1.79},"AZN":{"code":"AZN","value":1.7},"BAM":{"code":"BAM","value":1.823880354},"BBD":{"code":"BBD","value":2},"BDT":{"code":"BDT","value":117.462129783},"BGN":{"code":"BGN","value":1.8205203258},"BHD":{"code":"BHD","value":0.376},"BIF":{"code":"BIF","value":2873.5724425505},"BMD":{"code":"BMD","value":1},"BNB":{"code":"BNB","value":0.0017501226},"BND":{"code":"BND","value":1.3545502492},"BOB":{"code":"BOB","value":6.9256012708},"BRL":{"code":"BRL","value":5.5953807095},"BSD":{"code":"BSD","value":1},"BTC":{"code":"BTC","value":1.65569e-5},"BTN":{"code":"BTN","value":83.4565415655},"BWP":{"code":"BWP","value":13.6750415295},"BYN":{"code":"BYN","value":3.2741776811},"BYR":{"code":"BYR","value":32741.782773946},"BZD":{"code":"BZD","value":2},"CAD":{"code":"CAD","value":1.3671401741},"CDF":{"code":"CDF","value":2843.5465651148},"CHF":{"code":"CHF","value":0.8979801474},"CLF":{"code":"CLF","value":0.0245800026},"CLP":{"code":"CLP","value":940.4465266645},"CNY":{"code":"CNY","value":7.258451351},"COP":{"code":"COP","value":4145.4574132322},"CRC":{"code":"CRC","value":523.0663715433},"CUC":{"code":"CUC","value":1},"CUP":{"code":"CUP","value":24},"CVE":{"code":"CVE","value":102.8721559791},"CZK":{"code":"CZK","value":23.4234844059},"DAI":{"code":"DAI","value":0.99973929},"DJF":{"code":"DJF","value":177.721},"DKK":{"code":"DKK","value":6.9592807448},"DOP":{"code":"DOP","value":58.9404084},"DOT":{"code":"DOT","value":0.1617962741},"DZD":{"code":"DZD","value":134.8744337585},"EGP":{"code":"EGP","value":47.9834983374},"ERN":{"code":"ERN","value":15},"ETB":{"code":"ETB","value":57.7358994456},"ETH":{"code":"ETH","value":0.0002962933},"EUR":{"code":"EUR","value":0.9324901567},"FJD":{"code":"FJD","value":2.2365102259},"FKP":{"code":"FKP","value":0.790727324},"GBP":{"code":"GBP","value":0.7905701256},"GEL":{"code":"GEL","value":2.8258903324},"GGP":{"code":"GGP","value":0.7907268426},"GHS":{"code":"GHS","value":15.1635324534},"GIP":{"code":"GIP","value":0.7907268159},"GMD":{"code":"GMD","value":58.5607775241},"GNF":{"code":"GNF","value":8571.5996863372},"GTQ":{"code":"GTQ","value":7.7513810036},"GYD":{"code":"GYD","value":208.6757594524},"HKD":{"code":"HKD","value":7.8027812258},"HNL":{"code":"HNL","value":24.7189933803},"HRK":{"code":"HRK","value":6.6925607753},"HTG":{"code":"HTG","value":134.5408215743},"HUF":{"code":"HUF","value":368.279213549},"IDR":{"code":"IDR","value":16334.919165908},"ILS":{"code":"ILS","value":3.7635205769},"IMP":{"code":"IMP","value":0.7907272861},"INR":{"code":"INR","value":83.2928939949},"IQD":{"code":"IQD","value":1306.5200705869},"IRR":{"code":"IRR","value":41952.080900428},"ISK":{"code":"ISK","value":138.8944860643},"JEP":{"code":"JEP","value":0.7907272347},"JMD":{"code":"JMD","value":156.0000608007},"JOD":{"code":"JOD","value":0.71},"JPY":{"code":"JPY","value":160.8296379653},"KES":{"code":"KES","value":129.406073695},"KGS":{"code":"KGS","value":86.3729495499},"KHR":{"code":"KHR","value":4101.5175832139},"KMF":{"code":"KMF","value":459.569525714},"KPW":{"code":"KPW","value":900.013886773},"KRW":{"code":"KRW","value":1378.7306680635},"KWD":{"code":"KWD","value":0.3063600493},"KYD":{"code":"KYD","value":0.83333},"KZT":{"code":"KZT","value":472.3799197171},"LAK":{"code":"LAK","value":22059.202184897},"LBP":{"code":"LBP","value":89448.272181952},"LKR":{"code":"LKR","value":305.4431150956},"LRD":{"code":"LRD","value":194.4810579948},"LSL":{"code":"LSL","value":18.1760824616},"LTC":{"code":"LTC","value":0.0137197004},"LTL":{"code":"LTL","value":3.2219848413},"LVL":{"code":"LVL","value":0.6558191484},"LYD":{"code":"LYD","value":4.865720589},"MAD":{"code":"MAD","value":9.9486112447},"MATIC":{"code":"MATIC","value":1.8113859829},"MDL":{"code":"MDL","value":17.7828521852},"MGA":{"code":"MGA","value":4498.1864954395},"MKD":{"code":"MKD","value":57.4833883387},"MMK":{"code":"MMK","value":2092.2518978649},"MNT":{"code":"MNT","value":3386.2423690251},"MOP":{"code":"MOP","value":8.0262609136},"MRO":{"code":"MRO","value":356.999828},"MRU":{"code":"MRU","value":39.4629601451},"MUR":{"code":"MUR","value":47.0342676649},"MVR":{"code":"MVR","value":15.438811821},"MWK":{"code":"MWK","value":1732.7401462781},"MXN":{"code":"MXN","value":18.3205926031},"MYR":{"code":"MYR","value":4.7116906124},"MZN":{"code":"MZN","value":63.5066584337},"NAD":{"code":"NAD","value":18.139313595},"NGN":{"code":"NGN","value":1511.4358945244},"NIO":{"code":"NIO","value":36.8054758517},"NOK":{"code":"NOK","value":10.6764120532},"NPR":{"code":"NPR","value":133.3272857501},"NZD":{"code":"NZD","value":1.6405403203},"OMR":{"code":"OMR","value":0.3836200483},"OP":{"code":"OP","value":0.5720239909},"PAB":{"code":"PAB","value":0.9987601759},"PEN":{"code":"PEN","value":3.83213042},"PGK":{"code":"PGK","value":3.8447407499},"PHP":{"code":"PHP","value":58.4127010836},"PKR":{"code":"PKR","value":277.9154514127},"PLN":{"code":"PLN","value":4.02482058},"PYG":{"code":"PYG","value":7554.5309148295},"QAR":{"code":"QAR","value":3.6355203864},"RON":{"code":"RON","value":4.6457105561},"RSD":{"code":"RSD","value":108.7903610487},"RUB":{"code":"RUB","value":86.1460667514},"RWF":{"code":"RWF","value":1304.9309934412},"SAR":{"code":"SAR","value":3.7409605213},"SBD":{"code":"SBD","value":8.2304632858},"SCR":{"code":"SCR","value":14.7263417779},"SDG":{"code":"SDG","value":601.5},"SEK":{"code":"SEK","value":10.5925316711},"SGD":{"code":"SGD","value":1.3544102549},"SHP":{"code":"SHP","value":0.7905700876},"SLL":{"code":"SLL","value":22416.380257554},"SOL":{"code":"SOL","value":0.0071555843},"SOS":{"code":"SOS","value":571.4265192725},"SRD":{"code":"SRD","value":30.8114444737},"STD":{"code":"STD","value":22897.513012757},"STN":{"code":"STN","value":22.8975141533},"SVC":{"code":"SVC","value":8.75},"SYP":{"code":"SYP","value":12994.511322126},"SZL":{"code":"SZL","value":18.1755232352},"THB":{"code":"THB","value":36.7586652668},"TJS":{"code":"TJS","value":10.6602816847},"TMT":{"code":"TMT","value":3.5},"TND":{"code":"TND","value":3.1354005948},"TOP":{"code":"TOP","value":2.3328904106},"TRY":{"code":"TRY","value":32.6424051445},"TTD":{"code":"TTD","value":6.7942407768},"TWD":{"code":"TWD","value":32.5294342459},"TZS":{"code":"TZS","value":2649.3351887268},"UAH":{"code":"UAH","value":40.6162545747},"UGX":{"code":"UGX","value":3701.662972606},"USD":{"code":"USD","value":1},"USDC":{"code":"USDC","value":0.999769745},"USDT":{"code":"USDT","value":1.0011944592},"UYU":{"code":"UYU","value":39.4245468671},"UZS":{"code":"UZS","value":12540.182476233},"VEF":{"code":"VEF","value":3640282.9537041},"VES":{"code":"VES","value":36.4028365777},"VND":{"code":"VND","value":25413.749120129},"VUV":{"code":"VUV","value":118.891649178},"WST":{"code":"WST","value":2.73189145},"XAF":{"code":"XAF","value":611.9392780017},"XAG":{"code":"XAG","value":0.0343132757},"XAU":{"code":"XAU","value":0.0004298664},"XCD":{"code":"XCD","value":2.7},"XDR":{"code":"XDR","value":0.7588801012},"XOF":{"code":"XOF","value":611.9392515807},"XPD":{"code":"XPD","value":0.0010416687},"XPF":{"code":"XPF","value":111.2490363256},"XPT":{"code":"XPT","value":0.0011144678},"XRP":{"code":"XRP","value":2.1234336693},"YER":{"code":"YER","value":249.539521989},"ZAR":{"code":"ZAR","value":18.1474632173},"ZMK":{"code":"ZMK","value":9001.2},"ZMW":{"code":"ZMW","value":24.0634536674},"ZWL":{"code":"ZWL","value":13.668785494}}}