{"meta":{"last_updated_at":"2024-01-21T23:59:59Z"},"data":{"ADA":{"code":"ADA","value":1.9842397757},"AED":{"code":"AED","value":3.6725207173},"AFN":{"code":"AFN","value":72.1043399165},"ALL":{"code":"ALL","value":95.0860869798},"AMD":{"code":"AMD","value":404.470618528},"ANG":{"code":"ANG","value":1.7857202372},"AOA":{"code":"AOA","value":827.1149211696},"ARB":{"code":"ARB","value":0.5498710412},"ARS":{"code":"ARS","value":819.1534219031},"AUD":{"code":"AUD","value":1.5163702272},"AVAX":{"code":"AVAX","value":0.0307011348},"AWG":{"code":"AWG","value":1.79},"AZN":{"code":"AZN","value":1.7},"BAM":{"code":"BAM","value":1.7981402947},"BBD":{"code":"BBD","value":2},"BDT":{"code":"BDT","value":109.5483216426},"BGN":{"code":"BGN","value":1.7879803259},"BHD":{"code":"BHD","value":0.376},"BIF":{"code":"BIF","value":2850.2438995979},"BMD":{"code":"BMD","value":1},"BNB":{"code":"BNB","value":0.0030132742},"BND":{"code":"BND","value":1.3394602269},"BOB":{"code":"BOB","value":6.9292207282},"BRL":{"code":"BRL","value":4.9318006913},"BSD":{"code":"BSD","value":1},"BTC":{"code":"BTC","value":2.39413e-5},"BTN":{"code":"BTN","value":83.038304043},"BWP":{"code":"BWP","value":13.638351913},"BYN":{"code":"BYN","value":3.2941612835},"BYR":{"code":"BYR","value":32941.588881418},"BZD":{"code":"BZD","value":2},"CAD":{"code":"CAD","value":1.3437001859},"CDF":{"code":"CDF","value":2660.0494334333},"CHF":{"code":"CHF","value":0.8684200985},"CLF":{"code":"CLF","value":0.0245500037},"CLP":{"code":"CLP","value":908.7381129676},"CNY":{"code":"CNY","value":7.1915913927},"COP":{"code":"COP","value":3909.9198222704},"CRC":{"code":"CRC","value":517.7561117963},"CUC":{"code":"CUC","value":1},"CUP":{"code":"CUP","value":24},"CVE":{"code":"CVE","value":101.2458273166},"CZK":{"code":"CZK","value":22.6992735599},"DAI":{"code":"DAI","value":0.9979367292},"DJF":{"code":"DJF","value":177.721},"DKK":{"code":"DKK","value":6.8454908512},"DOP":{"code":"DOP","value":58.6469467329},"DOT":{"code":"DOT","value":0.1464763111},"DZD":{"code":"DZD","value":134.9164736456},"EGP":{"code":"EGP","value":30.8802544839},"ERN":{"code":"ERN","value":15},"ETB":{"code":"ETB","value":56.5356892809},"ETH":{"code":"ETH","value":0.0004051848},"EUR":{"code":"EUR","value":0.9179601255},"FJD":{"code":"FJD","value":2.2361203145},"FKP":{"code":"FKP","value":0.7875213731},"GBP":{"code":"GBP","value":0.7874901529},"GEL":{"code":"GEL","value":2.6578004724},"GGP":{"code":"GGP","value":0.787521223},"GHS":{"code":"GHS","value":12.0032117521},"GIP":{"code":"GIP","value":0.7875216888},"GMD":{"code":"GMD","value":58.3324988004},"GNF":{"code":"GNF","value":8551.8890878586},"GTQ":{"code":"GTQ","value":7.8045610955},"GYD":{"code":"GYD","value":209.0663745037},"HKD":{"code":"HKD","value":7.8168414274},"HNL":{"code":"HNL","value":24.6350026642},"HRK":{"code":"HRK","value":7.0203609429},"HTG":{"code":"HTG","value":133.6462522242},"HUF":{"code":"HUF","value":350.510339614},"IDR":{"code":"IDR","value":15585.736871327},"ILS":{"code":"ILS","value":3.7426606827},"IMP":{"code":"IMP","value":0.7875215928},"INR":{"code":"INR","value":83.0091638346},"IQD":{"code":"IQD","value":1307.490732645},"IRR":{"code":"IRR","value":41976.445030777},"ISK":{"code":"ISK","value":136.6953959978},"JEP":{"code":"JEP","value":0.7875212889},"JMD":{"code":"JMD","value":154.6548599746},"JOD":{"code":"JOD","value":0.71},"JPY":{"code":"JPY","value":148.1297455523},"KES":{"code":"KES","value":159.1893028224},"KGS":{"code":"KGS","value":89.1570873904},"KHR":{"code":"KHR","value":4065.7085431043},"KMF":{"code":"KMF","value":452.6208164842},"KPW":{"code":"KPW","value":899.9809737628},"KRW":{"code":"KRW","value":1333.2495158159},"KWD":{"code":"KWD","value":0.3067500442},"KYD":{"code":"KYD","value":0.83333},"KZT":{"code":"KZT","value":448.9519303337},"LAK":{"code":"LAK","value":20680.944341547},"LBP":{"code":"LBP","value":15001.41966619},"LKR":{"code":"LKR","value":319.0572620507},"LRD":{"code":"LRD","value":189.127972387},"LSL":{"code":"LSL","value":18.9111421495},"LTC":{"code":"LTC","value":0.0139135225},"LTL":{"code":"LTL","value":3.1702182507},"LVL":{"code":"LVL","value":0.6452819357},"LYD":{"code":"LYD","value":4.8099107401},"MAD":{"code":"MAD","value":9.9530715624},"MATIC":{"code":"MATIC","value":1.2750966968},"MDL":{"code":"MDL","value":17.6435234854},"MGA":{"code":"MGA","value":4565.5120349664},"MKD":{"code":"MKD","value":56.4943502188},"MMK":{"code":"MMK","value":2093.5775343258},"MNT":{"code":"MNT","value":3423.485629426},"MOP":{"code":"MOP","value":8.0438813277},"MRO":{"code":"MRO","value":356.999828},"MUR":{"code":"MUR","value":44.2266983097},"MVR":{"code":"MVR","value":15.4417018636},"MWK":{"code":"MWK","value":1682.6581109688},"MXN":{"code":"MXN","value":17.0881024502},"MYR":{"code":"MYR","value":4.7128509183},"MZN":{"code":"MZN","value":63.6689969455},"NAD":{"code":"NAD","value":18.954533119},"NGN":{"code":"NGN","value":889.8147412768},"NIO":{"code":"NIO","value":36.5744876965},"NOK":{"code":"NOK","value":10.4824911867},"NPR":{"code":"NPR","value":132.6642481304},"NZD":{"code":"NZD","value":1.6346402629},"OMR":{"code":"OMR","value":0.3838400642},"OP":{"code":"OP","value":0.3204871538},"PAB":{"code":"PAB","value":0.9989401051},"PEN":{"code":"PEN","value":3.7424504006},"PGK":{"code":"PGK","value":3.7322504727},"PHP":{"code":"PHP","value":55.9425464873},"PKR":{"code":"PKR","value":279.6332348632},"PLN":{"code":"PLN","value":3.993110752},"PYG":{"code":"PYG","value":7315.2166896995},"QAR":{"code":"QAR","value":3.6369406092},"RON":{"code":"RON","value":4.5695108196},"RSD":{"code":"RSD","value":107.2228553586},"RUB":{"code":"RUB","value":88.025467258},"RWF":{"code":"RWF","value":1266.43113964},"SAR":{"code":"SAR","value":3.7449305161},"SBD":{"code":"SBD","value":8.2919513054},"SCR":{"code":"SCR","value":14.3441020178},"SDG":{"code":"SDG","value":601.5},"SEK":{"code":"SEK","value":10.4569813764},"SGD":{"code":"SGD","value":1.3405201969},"SHP":{"code":"SHP","value":0.7874901021},"SLL":{"code":"SLL","value":22735.343288852},"SOL":{"code":"SOL","value":0.0109783535},"SOS":{"code":"SOS","value":570.9724526988},"SRD":{"code":"SRD","value":36.6479837699},"STD":{"code":"STD","value":22293.849013823},"SVC":{"code":"SVC","value":8.75},"SYP":{"code":"SYP","value":13001.87160278},"SZL":{"code":"SZL","value":19.006743266},"THB":{"code":"THB","value":35.5467570338},"TJS":{"code":"TJS","value":10.9519920908},"TMT":{"code":"TMT","value":3.5},"TND":{"code":"TND","value":3.0994003521},"TOP":{"code":"TOP","value":2.3433802516},"TRY":{"code":"TRY","value":30.1884554001},"TTD":{"code":"TTD","value":6.7946408026},"TWD":{"code":"TWD","value":31.4335440557},"TZS":{"code":"TZS","value":2510.8283680551},"UAH":{"code":"UAH","value":37.8087343285},"UGX":{"code":"UGX","value":3809.664759191},"USD":{"code":"USD","value":1},"USDC":{"code":"USDC","value":0.9981956832},"USDT":{"code":"USDT","value":0.9982099609},"UYU":{"code":"UYU","value":39.3626150592},"UZS":{"code":"UZS","value":12396.486131334},"VEF":{"code":"VEF","value":3609542.0128032},"VND":{"code":"VND","value":24520.739133204},"VUV":{"code":"VUV","value":120.074131881},"WST":{"code":"WST","value":2.7383367456},"XAF":{"code":"XAF","value":602.1908597071},"XAG":{"code":"XAG","value":0.0444038619},"XAU":{"code":"XAU","value":0.0004932253},"XCD":{"code":"XCD","value":2.7},"XDR":{"code":"XDR","value":0.7485901435},"XOF":{"code":"XOF","value":602.1908706952},"XPD":{"code":"XPD","value":0.0010537193},"XPF":{"code":"XPF","value":109.4609069657},"XPT":{"code":"XPT","value":0.001106391},"XRP":{"code":"XRP","value":1.8170641402},"YER":{"code":"YER","value":249.6787357336},"ZAR":{"code":"ZAR","value":19.0066619997},"ZMK":{"code":"ZMK","value":9001.2},"ZMW":{"code":"ZMW","value":26.4761540784},"ZWL":{"code":"ZWL","value":361.9}}}