{"meta":{"last_updated_at":"2026-05-16T23:59:59Z"},"data":{"ADA":{"code":"ADA","value":3.9181407375},"AED":{"code":"AED","value":3.6732004803},"AFN":{"code":"AFN","value":63.667311829},"ALL":{"code":"ALL","value":81.800012782},"AMD":{"code":"AMD","value":368.2300614973},"ANG":{"code":"ANG","value":1.7880002776},"AOA":{"code":"AOA","value":913.1161579623},"ARB":{"code":"ARB","value":8.3425109845},"ARS":{"code":"ARS","value":1394.9202336661},"AUD":{"code":"AUD","value":1.3990002359},"AVAX":{"code":"AVAX","value":0.107620725},"AWG":{"code":"AWG","value":1.79},"AZN":{"code":"AZN","value":1.7},"BAM":{"code":"BAM","value":1.6823001759},"BBD":{"code":"BBD","value":2},"BDT":{"code":"BDT","value":122.6700126659},"BGN":{"code":"BGN","value":1.6650003061},"BHD":{"code":"BHD","value":0.376},"BIF":{"code":"BIF","value":2977.0005467892},"BMD":{"code":"BMD","value":1},"BNB":{"code":"BNB","value":0.0015230425},"BND":{"code":"BND","value":1.2810002158},"BOB":{"code":"BOB","value":6.9100009762},"BRL":{"code":"BRL","value":5.0706008703},"BSD":{"code":"BSD","value":1},"BTC":{"code":"BTC","value":1.2793e-5},"BTN":{"code":"BTN","value":96.061769478},"BWP":{"code":"BWP","value":13.1234018819},"BYN":{"code":"BYN","value":2.7819709994},"BYR":{"code":"BYR","value":27819.710122999},"BZD":{"code":"BZD","value":2},"CAD":{"code":"CAD","value":1.3750001482},"CDF":{"code":"CDF","value":2248.0002799938},"CHF":{"code":"CHF","value":0.7868001197},"CLF":{"code":"CLF","value":0.0224800034},"CLP":{"code":"CLP","value":909.7801797497},"CNY":{"code":"CNY","value":6.8099013299},"COP":{"code":"COP","value":3792.4804152273},"CRC":{"code":"CRC","value":453.4912841693},"CUC":{"code":"CUC","value":1},"CUP":{"code":"CUP","value":24},"CVE":{"code":"CVE","value":95.0995176758},"CZK":{"code":"CZK","value":20.915303886},"DAI":{"code":"DAI","value":0.99985079},"DJF":{"code":"DJF","value":177.721},"DKK":{"code":"DKK","value":6.4288010289},"DOP":{"code":"DOP","value":59.3000081342},"DOT":{"code":"DOT","value":0.7883939338},"DZD":{"code":"DZD","value":132.602017629},"EGP":{"code":"EGP","value":52.8958084284},"ERN":{"code":"ERN","value":15},"ETB":{"code":"ETB","value":157.5500229043},"ETH":{"code":"ETH","value":0.0004585201},"EUR":{"code":"EUR","value":0.860182098},"FJD":{"code":"FJD","value":2.20460033},"FKP":{"code":"FKP","value":0.7502933724},"GBP":{"code":"GBP","value":0.7504701483},"GEL":{"code":"GEL","value":2.6802004415},"GGP":{"code":"GGP","value":0.7502933803},"GHS":{"code":"GHS","value":11.4400016948},"GIP":{"code":"GIP","value":0.7502933404},"GMD":{"code":"GMD","value":73.0000093085},"GNF":{"code":"GNF","value":8785.0010951462},"GTQ":{"code":"GTQ","value":7.6250010695},"GYD":{"code":"GYD","value":208.8900220864},"HKD":{"code":"HKD","value":7.8298010796},"HNL":{"code":"HNL","value":26.6556049197},"HRK":{"code":"HRK","value":6.482040721},"HTG":{"code":"HTG","value":132.8800222949},"HUF":{"code":"HUF","value":311.1000621559},"IDR":{"code":"IDR","value":17470.002787886},"ILS":{"code":"ILS","value":2.9170005753},"IMP":{"code":"IMP","value":0.7502933694},"INR":{"code":"INR","value":95.9881150542},"IQD":{"code":"IQD","value":1310.0001841531},"IRR":{"code":"IRR","value":1318379.966754},"ISK":{"code":"ISK","value":123.5300223798},"JEP":{"code":"JEP","value":0.7502933578},"JMD":{"code":"JMD","value":157.7300304592},"JOD":{"code":"JOD","value":0.71},"JPY":{"code":"JPY","value":158.7500212749},"KES":{"code":"KES","value":129.3160391711},"KGS":{"code":"KGS","value":87.4500145588},"KHR":{"code":"KHR","value":4005.9954773538},"KMF":{"code":"KMF","value":422.5000642973},"KPW":{"code":"KPW","value":900.000064268},"KRW":{"code":"KRW","value":1498.4351986715},"KWD":{"code":"KWD","value":0.308640045},"KYD":{"code":"KYD","value":0.83333},"KZT":{"code":"KZT","value":470.540054358},"LAK":{"code":"LAK","value":21803.103400515},"LBP":{"code":"LBP","value":89500.013089735},"LKR":{"code":"LKR","value":327.0000645798},"LRD":{"code":"LRD","value":183.380023876},"LSL":{"code":"LSL","value":16.6800024269},"LTC":{"code":"LTC","value":0.0178065457},"LTL":{"code":"LTL","value":2.9704944604},"LVL":{"code":"LVL","value":0.604629087},"LYD":{"code":"LYD","value":6.3200009643},"MAD":{"code":"MAD","value":9.2121012734},"MATIC":{"code":"MATIC","value":10.9704206617},"MDL":{"code":"MDL","value":17.0530021678},"MGA":{"code":"MGA","value":4183.0004994581},"MKD":{"code":"MKD","value":52.7600077589},"MMK":{"code":"MMK","value":2098.6803487635},"MNT":{"code":"MNT","value":3579.295849283},"MOP":{"code":"MOP","value":8.0647013631},"MRO":{"code":"MRO","value":356.999828},"MRU":{"code":"MRU","value":40.0208401351},"MUR":{"code":"MUR","value":47.1395066069},"MVR":{"code":"MVR","value":15.4600024974},"MWK":{"code":"MWK","value":1733.6732933984},"MXN":{"code":"MXN","value":17.3350020221},"MYR":{"code":"MYR","value":3.9500007173},"MZN":{"code":"MZN","value":63.5500065842},"NAD":{"code":"NAD","value":16.6916025136},"NGN":{"code":"NGN","value":1370.4652332059},"NIO":{"code":"NIO","value":36.6766665169},"NOK":{"code":"NOK","value":9.311181027},"NPR":{"code":"NPR","value":153.4860252597},"NZD":{"code":"NZD","value":1.713000287},"OMR":{"code":"OMR","value":0.38510004},"OP":{"code":"OP","value":7.5179377205},"PAB":{"code":"PAB","value":1.0000001782},"PEN":{"code":"PEN","value":3.4341004626},"PGK":{"code":"PGK","value":4.361100779},"PHP":{"code":"PHP","value":61.6970094878},"PKR":{"code":"PKR","value":278.6300495581},"PLN":{"code":"PLN","value":3.6502006089},"PYG":{"code":"PYG","value":6091.0908714841},"QAR":{"code":"QAR","value":3.6450007178},"RON":{"code":"RON","value":4.4450905336},"RSD":{"code":"RSD","value":100.9930188785},"RUB":{"code":"RUB","value":72.8500086722},"RWF":{"code":"RWF","value":1461.0002141694},"SAR":{"code":"SAR","value":3.7526104087},"SBD":{"code":"SBD","value":8.0160168984},"SCR":{"code":"SCR","value":14.7100016953},"SDG":{"code":"SDG","value":601.5},"SEK":{"code":"SEK","value":9.4504017689},"SGD":{"code":"SGD","value":1.2806701726},"SHP":{"code":"SHP","value":0.7505001387},"SLE":{"code":"SLE","value":22.9293282025},"SLL":{"code":"SLL","value":22840.502839652},"SOL":{"code":"SOL","value":0.0115481163},"SOS":{"code":"SOS","value":571.450109983},"SRD":{"code":"SRD","value":37.1950059211},"STD":{"code":"STD","value":21138.240745489},"STN":{"code":"STN","value":21.1382423816},"SVC":{"code":"SVC","value":8.75},"SYP":{"code":"SYP","value":110.5250005602},"SZL":{"code":"SZL","value":16.6709026478},"THB":{"code":"THB","value":32.6800056666},"TJS":{"code":"TJS","value":9.3520009652},"TMT":{"code":"TMT","value":3.5},"TND":{"code":"TND","value":2.8960005505},"TOP":{"code":"TOP","value":2.3635002789},"TRX":{"code":"TRX","value":2.828673578},"TRY":{"code":"TRY","value":45.4933060747},"TTD":{"code":"TTD","value":6.7578011026},"TWD":{"code":"TWD","value":31.5790034756},"TZS":{"code":"TZS","value":2573.0004227806},"UAH":{"code":"UAH","value":44.0819049531},"UGX":{"code":"UGX","value":3754.9003900452},"USD":{"code":"USD","value":1},"USDC":{"code":"USDC","value":0.9993941355},"USDT":{"code":"USDT","value":1.0000971807},"UYU":{"code":"UYU","value":40.1240052106},"UZS":{"code":"UZS","value":11986.301618857},"VEF":{"code":"VEF","value":51432220.634768},"VES":{"code":"VES","value":514.3222306519},"VND":{"code":"VND","value":26350.004247956},"VUV":{"code":"VUV","value":117.2887823899},"WST":{"code":"WST","value":2.7063804006},"XAF":{"code":"XAF","value":564.2200915439},"XAG":{"code":"XAG","value":0.013164248},"XAU":{"code":"XAU","value":0.0002203737},"XCD":{"code":"XCD","value":2.7},"XCG":{"code":"XCG","value":1.7957551175},"XDR":{"code":"XDR","value":0.7287101324},"XOF":{"code":"XOF","value":564.2200598077},"XPD":{"code":"XPD","value":0.0007059773},"XPF":{"code":"XPF","value":102.9000175619},"XPT":{"code":"XPT","value":0.0005054363},"XRP":{"code":"XRP","value":0.7067537843},"YER":{"code":"YER","value":238.5950453875},"ZAR":{"code":"ZAR","value":16.6986021624},"ZMK":{"code":"ZMK","value":9001.2},"ZMW":{"code":"ZMW","value":18.9100027111},"ZWG":{"code":"ZWG","value":25.7707771849},"ZWL":{"code":"ZWL","value":64394.069273969}}}