{"meta":{"last_updated_at":"2024-11-15T23:59:59Z"},"data":{"ADA":{"code":"ADA","value":1.4212589661},"AED":{"code":"AED","value":3.6715105967},"AFN":{"code":"AFN","value":68.0484425238},"ALL":{"code":"ALL","value":93.001409516},"AMD":{"code":"AMD","value":389.5310834901},"ANG":{"code":"ANG","value":1.7862503291},"AOA":{"code":"AOA","value":915.4829295044},"ARB":{"code":"ARB","value":1.6525210758},"ARS":{"code":"ARS","value":997.7657758354},"AUD":{"code":"AUD","value":1.5474602497},"AVAX":{"code":"AVAX","value":0.0302518004},"AWG":{"code":"AWG","value":1.79},"AZN":{"code":"AZN","value":1.7},"BAM":{"code":"BAM","value":1.8546402819},"BBD":{"code":"BBD","value":2},"BDT":{"code":"BDT","value":119.9887683879},"BGN":{"code":"BGN","value":1.8441702429},"BHD":{"code":"BHD","value":0.376},"BIF":{"code":"BIF","value":2899.1692514473},"BMD":{"code":"BMD","value":1},"BNB":{"code":"BNB","value":0.001624369},"BND":{"code":"BND","value":1.3417502593},"BOB":{"code":"BOB","value":6.9241707928},"BRL":{"code":"BRL","value":5.7942407539},"BSD":{"code":"BSD","value":1},"BTC":{"code":"BTC","value":1.0996e-5},"BTN":{"code":"BTN","value":84.6075334056},"BWP":{"code":"BWP","value":13.7607718878},"BYN":{"code":"BYN","value":3.2729862388},"BYR":{"code":"BYR","value":32729.887838969},"BZD":{"code":"BZD","value":2},"CAD":{"code":"CAD","value":1.4084701565},"CDF":{"code":"CDF","value":2849.1024215103},"CHF":{"code":"CHF","value":0.8872201696},"CLF":{"code":"CLF","value":0.0253500027},"CLP":{"code":"CLP","value":979.6453585002},"CNY":{"code":"CNY","value":7.2302614261},"COP":{"code":"COP","value":4421.9605495491},"CRC":{"code":"CRC","value":511.5104949638},"CUC":{"code":"CUC","value":1},"CUP":{"code":"CUP","value":24},"CVE":{"code":"CVE","value":104.6129239023},"CZK":{"code":"CZK","value":23.9525131907},"DAI":{"code":"DAI","value":1.0012508471},"DJF":{"code":"DJF","value":177.721},"DKK":{"code":"DKK","value":7.076640825},"DOP":{"code":"DOP","value":60.2000677251},"DOT":{"code":"DOT","value":0.1942658908},"DZD":{"code":"DZD","value":133.9463560702},"EGP":{"code":"EGP","value":49.3532385967},"ERN":{"code":"ERN","value":15},"ETB":{"code":"ETB","value":121.7358419826},"ETH":{"code":"ETH","value":0.0003240056},"EUR":{"code":"EUR","value":0.9482101317},"FJD":{"code":"FJD","value":2.2746703878},"FKP":{"code":"FKP","value":0.7925105105},"GBP":{"code":"GBP","value":0.7923201365},"GEL":{"code":"GEL","value":2.7438104386},"GGP":{"code":"GGP","value":0.792510007},"GHS":{"code":"GHS","value":15.9005231393},"GIP":{"code":"GIP","value":0.7925099188},"GMD":{"code":"GMD","value":58.6906901327},"GNF":{"code":"GNF","value":8598.459457955},"GTQ":{"code":"GTQ","value":7.7118210426},"GYD":{"code":"GYD","value":208.8391960728},"HKD":{"code":"HKD","value":7.7831611779},"HNL":{"code":"HNL","value":25.0808639439},"HRK":{"code":"HRK","value":6.7074111916},"HTG":{"code":"HTG","value":133.4772947945},"HUF":{"code":"HUF","value":387.8022145019},"IDR":{"code":"IDR","value":15830.634495439},"ILS":{"code":"ILS","value":3.7449006444},"IMP":{"code":"IMP","value":0.7925100117},"INR":{"code":"INR","value":84.3785490024},"IQD":{"code":"IQD","value":1307.8259627924},"IRR":{"code":"IRR","value":42003.71331101},"ISK":{"code":"ISK","value":137.5038834917},"JEP":{"code":"JEP","value":0.7925103572},"JMD":{"code":"JMD","value":158.2001888132},"JOD":{"code":"JOD","value":0.71},"JPY":{"code":"JPY","value":154.3273042766},"KES":{"code":"KES","value":129.4953471661},"KGS":{"code":"KGS","value":86.7634571845},"KHR":{"code":"KHR","value":4034.1497794996},"KMF":{"code":"KMF","value":466.007781039},"KPW":{"code":"KPW","value":900.0161517238},"KRW":{"code":"KRW","value":1391.9707805498},"KWD":{"code":"KWD","value":0.3074300409},"KYD":{"code":"KYD","value":0.83333},"KZT":{"code":"KZT","value":495.8926741801},"LAK":{"code":"LAK","value":21972.573200831},"LBP":{"code":"LBP","value":89551.639348272},"LKR":{"code":"LKR","value":293.1884429512},"LRD":{"code":"LRD","value":183.9015918503},"LSL":{"code":"LSL","value":18.2175121832},"LTC":{"code":"LTC","value":0.0119493003},"LTL":{"code":"LTL","value":3.2751751119},"LVL":{"code":"LVL","value":0.6666453417},"LYD":{"code":"LYD","value":4.8795306042},"MAD":{"code":"MAD","value":9.9847110899},"MATIC":{"code":"MATIC","value":2.6801500903},"MDL":{"code":"MDL","value":18.0413828098},"MGA":{"code":"MGA","value":4664.8239709614},"MKD":{"code":"MKD","value":58.5232769402},"MMK":{"code":"MMK","value":2098.2880389632},"MNT":{"code":"MNT","value":3415.4457138092},"MOP":{"code":"MOP","value":8.0412214246},"MRO":{"code":"MRO","value":356.999828},"MRU":{"code":"MRU","value":39.9296677052},"MUR":{"code":"MUR","value":47.0580276507},"MVR":{"code":"MVR","value":15.4501618197},"MWK":{"code":"MWK","value":1733.4783919055},"MXN":{"code":"MXN","value":20.3265236847},"MYR":{"code":"MYR","value":4.4695904823},"MZN":{"code":"MZN","value":63.5738688325},"NAD":{"code":"NAD","value":18.1286918903},"NGN":{"code":"NGN","value":1658.0570249588},"NIO":{"code":"NIO","value":36.7609518647},"NOK":{"code":"NOK","value":11.0821618159},"NPR":{"code":"NPR","value":135.4668149573},"NZD":{"code":"NZD","value":1.7042703061},"OMR":{"code":"OMR","value":0.3839100764},"OP":{"code":"OP","value":0.6325092363},"PAB":{"code":"PAB","value":0.9990701854},"PEN":{"code":"PEN","value":3.8054807608},"PGK":{"code":"PGK","value":3.9633205593},"PHP":{"code":"PHP","value":58.7234974752},"PKR":{"code":"PKR","value":277.5162724908},"PLN":{"code":"PLN","value":4.094970567},"PYG":{"code":"PYG","value":7817.8141021367},"QAR":{"code":"QAR","value":3.6391506122},"RON":{"code":"RON","value":4.722110841},"RSD":{"code":"RSD","value":110.9174521556},"RUB":{"code":"RUB","value":99.9706951654},"RWF":{"code":"RWF","value":1363.0826719329},"SAR":{"code":"SAR","value":3.7405603807},"SBD":{"code":"SBD","value":8.3864537185},"SCR":{"code":"SCR","value":14.8205016088},"SDG":{"code":"SDG","value":601.5},"SEK":{"code":"SEK","value":10.972971508},"SGD":{"code":"SGD","value":1.3416701521},"SHP":{"code":"SHP","value":0.7923200834},"SLL":{"code":"SLL","value":22602.075572904},"SOL":{"code":"SOL","value":0.0045767886},"SOS":{"code":"SOS","value":571.381320008},"SRD":{"code":"SRD","value":35.063434199},"STD":{"code":"STD","value":23345.991236872},"STN":{"code":"STN","value":23.3459917952},"SVC":{"code":"SVC","value":8.75},"SYP":{"code":"SYP","value":13002.040789662},"SZL":{"code":"SZL","value":18.1633126479},"THB":{"code":"THB","value":34.898075202},"TJS":{"code":"TJS","value":10.6957414461},"TMT":{"code":"TMT","value":3.5},"TND":{"code":"TND","value":3.145830373},"TOP":{"code":"TOP","value":2.3626502384},"TRY":{"code":"TRY","value":34.4328166277},"TTD":{"code":"TTD","value":6.7841211161},"TWD":{"code":"TWD","value":32.5198359943},"TZS":{"code":"TZS","value":2652.4872236869},"UAH":{"code":"UAH","value":41.3589979697},"UGX":{"code":"UGX","value":3668.1595427028},"USD":{"code":"USD","value":1},"USDC":{"code":"USDC","value":1.0012544569},"USDT":{"code":"USDT","value":1.0007017922},"UYU":{"code":"UYU","value":42.9024453168},"UZS":{"code":"UZS","value":12838.739671662},"VEF":{"code":"VEF","value":4573304.9597134},"VES":{"code":"VES","value":45.7330360237},"VND":{"code":"VND","value":25372.436158511},"VUV":{"code":"VUV","value":121.349035344},"WST":{"code":"WST","value":2.79045301},"XAF":{"code":"XAF","value":622.2533008434},"XAG":{"code":"XAG","value":0.0330628247},"XAU":{"code":"XAU","value":0.0003902726},"XCD":{"code":"XCD","value":2.7},"XDR":{"code":"XDR","value":0.7601200836},"XOF":{"code":"XOF","value":622.2533010841},"XPD":{"code":"XPD","value":0.0010416683},"XPF":{"code":"XPF","value":113.1090191035},"XPT":{"code":"XPT","value":0.0010615783},"XRP":{"code":"XRP","value":1.1227638657},"YER":{"code":"YER","value":249.4418587508},"ZAR":{"code":"ZAR","value":18.1621319318},"ZMK":{"code":"ZMK","value":9001.2},"ZMW":{"code":"ZMW","value":27.5852354755},"ZWL":{"code":"ZWL","value":63162.755888851}}}