{"meta":{"last_updated_at":"2024-09-22T23:59:59Z"},"data":{"ADA":{"code":"ADA","value":2.8398605334},"AED":{"code":"AED","value":3.6728305393},"AFN":{"code":"AFN","value":69.0096894799},"ALL":{"code":"ALL","value":88.7650389944},"AMD":{"code":"AMD","value":387.0382112168},"ANG":{"code":"ANG","value":1.7876301911},"AOA":{"code":"AOA","value":928.4229855519},"ARB":{"code":"ARB","value":1.6634060798},"ARS":{"code":"ARS","value":962.7955779893},"AUD":{"code":"AUD","value":1.468440252},"AVAX":{"code":"AVAX","value":0.0365702007},"AWG":{"code":"AWG","value":1.79},"AZN":{"code":"AZN","value":1.7},"BAM":{"code":"BAM","value":1.7525702686},"BBD":{"code":"BBD","value":2},"BDT":{"code":"BDT","value":120.0760427685},"BGN":{"code":"BGN","value":1.744500265},"BHD":{"code":"BHD","value":0.376},"BIF":{"code":"BIF","value":2892.6683644381},"BMD":{"code":"BMD","value":1},"BNB":{"code":"BNB","value":0.001699529},"BND":{"code":"BND","value":1.2900901509},"BOB":{"code":"BOB","value":6.9290511784},"BRL":{"code":"BRL","value":5.5176306704},"BSD":{"code":"BSD","value":1},"BTC":{"code":"BTC","value":1.57053e-5},"BTN":{"code":"BTN","value":83.7676354891},"BWP":{"code":"BWP","value":13.1639213968},"BYN":{"code":"BYN","value":3.2706708807},"BYR":{"code":"BYR","value":32706.707443482},"BZD":{"code":"BZD","value":2},"CAD":{"code":"CAD","value":1.3563502708},"CDF":{"code":"CDF","value":2848.1025656349},"CHF":{"code":"CHF","value":0.8507501498},"CLF":{"code":"CLF","value":0.0241900033},"CLP":{"code":"CLP","value":930.2632948954},"CNY":{"code":"CNY","value":7.0549213486},"COP":{"code":"COP","value":4153.4305619429},"CRC":{"code":"CRC","value":517.9642605432},"CUC":{"code":"CUC","value":1},"CUP":{"code":"CUP","value":24},"CVE":{"code":"CVE","value":98.7906654848},"CZK":{"code":"CZK","value":22.4528133159},"DAI":{"code":"DAI","value":0.9992551442},"DJF":{"code":"DJF","value":177.721},"DKK":{"code":"DKK","value":6.6827611546},"DOP":{"code":"DOP","value":60.1373170297},"DOT":{"code":"DOT","value":0.2313652456},"DZD":{"code":"DZD","value":132.9943334965},"EGP":{"code":"EGP","value":48.5852187583},"ERN":{"code":"ERN","value":15},"ETB":{"code":"ETB","value":115.8124973547},"ETH":{"code":"ETH","value":0.0003871032},"EUR":{"code":"EUR","value":0.8955901096},"FJD":{"code":"FJD","value":2.2025004061},"FKP":{"code":"FKP","value":0.7511202492},"GBP":{"code":"GBP","value":0.7511501196},"GEL":{"code":"GEL","value":2.7283604331},"GGP":{"code":"GGP","value":0.7511207816},"GHS":{"code":"GHS","value":15.6911718082},"GIP":{"code":"GIP","value":0.7511207895},"GMD":{"code":"GMD","value":55.6408457571},"GNF":{"code":"GNF","value":8650.1826944561},"GTQ":{"code":"GTQ","value":7.7253613962},"GYD":{"code":"GYD","value":209.0281300663},"HKD":{"code":"HKD","value":7.789811268},"HNL":{"code":"HNL","value":24.8328333734},"HRK":{"code":"HRK","value":6.3588612262},"HTG":{"code":"HTG","value":134.000133076},"HUF":{"code":"HUF","value":352.2688910408},"IDR":{"code":"IDR","value":15088.525697918},"ILS":{"code":"ILS","value":3.7858806822},"IMP":{"code":"IMP","value":0.7511202176},"INR":{"code":"INR","value":83.4972244875},"IQD":{"code":"IQD","value":1308.873608515},"IRR":{"code":"IRR","value":42034.499776273},"ISK":{"code":"ISK","value":136.1356530622},"JEP":{"code":"JEP","value":0.7511205562},"JMD":{"code":"JMD","value":157.5442058984},"JOD":{"code":"JOD","value":0.71},"JPY":{"code":"JPY","value":144.0099737306},"KES":{"code":"KES","value":128.7915375158},"KGS":{"code":"KGS","value":84.0673415716},"KHR":{"code":"KHR","value":4059.9426068484},"KMF":{"code":"KMF","value":441.0504697967},"KPW":{"code":"KPW","value":899.973918107},"KRW":{"code":"KRW","value":1330.9122597653},"KWD":{"code":"KWD","value":0.3052100426},"KYD":{"code":"KYD","value":0.83333},"KZT":{"code":"KZT","value":479.6859350488},"LAK":{"code":"LAK","value":22098.269635241},"LBP":{"code":"LBP","value":89607.834957114},"LKR":{"code":"LKR","value":304.2958611819},"LRD":{"code":"LRD","value":194.6300537273},"LSL":{"code":"LSL","value":17.5347221749},"LTC":{"code":"LTC","value":0.0145553179},"LTL":{"code":"LTL","value":3.0935442612},"LVL":{"code":"LVL","value":0.6296755456},"LYD":{"code":"LYD","value":4.7482905644},"MAD":{"code":"MAD","value":9.6740012828},"MATIC":{"code":"MATIC","value":2.4889162252},"MDL":{"code":"MDL","value":17.3504630225},"MGA":{"code":"MGA","value":4542.2113942738},"MKD":{"code":"MKD","value":55.3190570466},"MMK":{"code":"MMK","value":2096.0048542352},"MNT":{"code":"MNT","value":3400.5793358891},"MOP":{"code":"MOP","value":8.0275512954},"MRO":{"code":"MRO","value":356.999828},"MRU":{"code":"MRU","value":39.6903181334},"MUR":{"code":"MUR","value":45.8438157715},"MVR":{"code":"MVR","value":15.4593725389},"MWK":{"code":"MWK","value":1735.0918067255},"MXN":{"code":"MXN","value":19.3863822673},"MYR":{"code":"MYR","value":4.2070208099},"MZN":{"code":"MZN","value":63.6268664897},"NAD":{"code":"NAD","value":17.3848730857},"NGN":{"code":"NGN","value":1594.7841718299},"NIO":{"code":"NIO","value":36.8101827299},"NOK":{"code":"NOK","value":10.4838911846},"NPR":{"code":"NPR","value":133.3766717287},"NZD":{"code":"NZD","value":1.6036302039},"OMR":{"code":"OMR","value":0.3843900515},"OP":{"code":"OP","value":0.5900836374},"PAB":{"code":"PAB","value":0.9991701276},"PEN":{"code":"PEN","value":3.7535806034},"PGK":{"code":"PGK","value":3.8938004688},"PHP":{"code":"PHP","value":55.6950107262},"PKR":{"code":"PKR","value":278.1490519967},"PLN":{"code":"PLN","value":3.824520481},"PYG":{"code":"PYG","value":7830.6763826664},"QAR":{"code":"QAR","value":3.6420305797},"RON":{"code":"RON","value":4.4602705239},"RSD":{"code":"RSD","value":104.1245865261},"RUB":{"code":"RUB","value":93.0195611152},"RWF":{"code":"RWF","value":1336.0877491984},"SAR":{"code":"SAR","value":3.746590626},"SBD":{"code":"SBD","value":8.3402763457},"SCR":{"code":"SCR","value":14.99786194},"SDG":{"code":"SDG","value":601.5},"SEK":{"code":"SEK","value":10.166611257},"SGD":{"code":"SGD","value":1.2907701574},"SHP":{"code":"SHP","value":0.7511500891},"SLL":{"code":"SLL","value":22540.620879447},"SOL":{"code":"SOL","value":0.0068985866},"SOS":{"code":"SOS","value":570.729959162},"SRD":{"code":"SRD","value":30.0265956498},"STD":{"code":"STD","value":22078.734979128},"STN":{"code":"STN","value":22.0787322456},"SVC":{"code":"SVC","value":8.75},"SYP":{"code":"SYP","value":13027.750923592},"SZL":{"code":"SZL","value":17.3892232826},"THB":{"code":"THB","value":32.9222835554},"TJS":{"code":"TJS","value":10.6380315323},"TMT":{"code":"TMT","value":3.5},"TND":{"code":"TND","value":3.0225104441},"TOP":{"code":"TOP","value":2.3191904578},"TRY":{"code":"TRY","value":34.1398966478},"TTD":{"code":"TTD","value":6.8136212218},"TWD":{"code":"TWD","value":32.0444144995},"TZS":{"code":"TZS","value":2729.2405561037},"UAH":{"code":"UAH","value":41.5922970267},"UGX":{"code":"UGX","value":3702.7626709361},"USD":{"code":"USD","value":1},"USDC":{"code":"USDC","value":0.9997759299},"USDT":{"code":"USDT","value":0.9992879913},"UYU":{"code":"UYU","value":41.664107602},"UZS":{"code":"UZS","value":12690.324989214},"VEF":{"code":"VEF","value":3682992.9864807},"VES":{"code":"VES","value":36.8299299326},"VND":{"code":"VND","value":24235.294581333},"VUV":{"code":"VUV","value":119.017820348},"WST":{"code":"WST","value":2.6947549879},"XAF":{"code":"XAF","value":587.620361001},"XAG":{"code":"XAG","value":0.0321534579},"XAU":{"code":"XAU","value":0.0003816194},"XCD":{"code":"XCD","value":2.7},"XDR":{"code":"XDR","value":0.7381600922},"XOF":{"code":"XOF","value":587.6203705659},"XPD":{"code":"XPD","value":0.0009421167},"XPF":{"code":"XPF","value":106.8407445827},"XPT":{"code":"XPT","value":0.0010272128},"XRP":{"code":"XRP","value":1.6999056363},"YER":{"code":"YER","value":249.9928884115},"ZAR":{"code":"ZAR","value":17.4281329572},"ZMK":{"code":"ZMK","value":9001.2},"ZMW":{"code":"ZMW","value":26.5619141255},"ZWL":{"code":"ZWL","value":35211.274916526}}}